{"file_name": "СМГ Мессояха/СМГ/Сводки 2021/Май/Сводка СМГ по Обустройству _ПС 31.05.2021 (Проект 108 ).xlsb", "work": [{"work title": "Укладка полосового заземления", "work id": "1", "upper works": ["Проект: ОКС 108.17 - Куст-88 ОКС 108.17 - Куст №88. Уровень 4", "WBS: ОКС 108.17 - Куст-88.3.2 Обустройство куста", "WBS: ОКС 108.17 - Куст-88.3.2.1 Подэтап 1", "WBS: ОКС 108.17 - Куст-88.3.2.1.9 Электрические сети (ЭС)"], "measurements": "мп", "amount": 629, "work_data": {"start_date": {"plan": "15.11.2019", "estimate": null, "fact": null}, "stop_date": {"plan": "05.05.2020", "estimate": null, "fact": null}, "complite_state_perc": {"plan": 100.0, "fact": 9.85691573926868}, "complite_state_value": {"plan": 629, "fact": 62}, "current_remain_perc": 100.0, "current_remain_value": 600, "whole_remain_perc": 90.14308426073131, "whole_remain_value": 567, "mounth_complite_perc": {"plan": 100.0, "fact": 0.0}, "mounth_complite_value": {"plan": 600, "fact": 0}, "progress": [{"01.05.2021": {"plan": 0, "fact": 0}}, {"02.05.2021": {"plan": 0, "fact": 0}}, {"03.05.2021": {"plan": 0, "fact": 0}}, {"04.05.2021": {"plan": 0, "fact": 0}}, {"05.05.2021": {"plan": 0, "fact": 0}}, {"06.05.2021": {"plan": 0, "fact": 0}}, {"07.05.2021": {"plan": 0, "fact": 0}}, {"08.05.2021": {"plan": 0, "fact": 0}}, {"09.05.2021": {"plan": 0, "fact": 0}}, {"10.05.2021": {"plan": 0, "fact": 0}}, {"11.05.2021": {"plan": 0, "fact": 0}}, {"12.05.2021": {"plan": 0, "fact": 0}}, {"13.05.2021": {"plan": 0, "fact": 0}}, {"14.05.2021": {"plan": 0, "fact": 0}}, {"15.05.2021": {"plan": 50, "fact": 0}}, {"16.05.2021": {"plan": 50, "fact": 0}}, {"17.05.2021": {"plan": 50, "fact": 0}}, {"18.05.2021": {"plan": 50, "fact": 0}}, {"19.05.2021": {"plan": 50, "fact": 0}}, {"20.05.2021": {"plan": 50, "fact": 0}}, {"21.05.2021": {"plan": 50, "fact": 0}}, {"22.05.2021": {"plan": 50, "fact": 0}}, {"23.05.2021": {"plan": 50, "fact": 0}}, {"24.05.2021": {"plan": 50, "fact": 0}}, {"25.05.2021": {"plan": 50, "fact": 0}}, {"26.05.2021": {"plan": 50, "fact": 0}}, {"27.05.2021": {"plan": 0, "fact": 0}}, {"28.05.2021": {"plan": 0, "fact": 0}}, {"29.05.2021": {"plan": 0, "fact": 0}}, {"30.05.2021": {"plan": 0, "fact": 0}}, {"31.05.2021": {"plan": 0, "fact": 0}}], "comments": null}, "guid": "S88-27560"}, {"work title": "Монтаж приборов АСУТП", "work id": "2", "upper works": ["Проект: ОКС 108.17 - Куст-88 ОКС 108.17 - Куст №88. Уровень 4", "WBS: ОКС 108.17 - Куст-88.3.2 Обустройство куста", "WBS: ОКС 108.17 - Куст-88.3.2.1 Подэтап 1", "WBS: ОКС 108.17 - Куст-88.3.2.1.11 Сети автоматизированной системы управления (АК)"], "measurements": "шт", "amount": 14, "work_data": {"start_date": {"plan": "15.11.2019", "estimate": null, "fact": null}, "stop_date": {"plan": "05.05.2020", "estimate": null, "fact": null}, "complite_state_perc": {"plan": 100.0, "fact": 100.0}, "complite_state_value": {"plan": 14, "fact": 14}, "current_remain_perc": 0, "current_remain_value": 0, "whole_remain_perc": 0, "whole_remain_value": 0, "mounth_complite_perc": {"plan": 100.0, "fact": 100.0}, "mounth_complite_value": {"plan": 1, "fact": 1}, "progress": [{"01.05.2021": {"plan": 0, "fact": 0}}, {"02.05.2021": {"plan": 0, "fact": 0}}, {"03.05.2021": {"plan": 0, "fact": 0}}, {"04.05.2021": {"plan": 0, "fact": 0}}, {"05.05.2021": {"plan": 0, "fact": 0}}, {"06.05.2021": {"plan": 0, "fact": 0}}, {"07.05.2021": {"plan": 0, "fact": 0}}, {"08.05.2021": {"plan": 0, "fact": 0}}, {"09.05.2021": {"plan": 0, "fact": 0}}, {"10.05.2021": {"plan": 0, "fact": 0}}, {"11.05.2021": {"plan": 0, "fact": 0}}, {"12.05.2021": {"plan": 0, "fact": 0}}, {"13.05.2021": {"plan": 0, "fact": 0}}, {"14.05.2021": {"plan": 0, "fact": 0}}, {"15.05.2021": {"plan": 0, "fact": 0}}, {"16.05.2021": {"plan": 0, "fact": 0}}, {"17.05.2021": {"plan": 0, "fact": 0}}, {"18.05.2021": {"plan": 0, "fact": 0}}, {"19.05.2021": {"plan": 0, "fact": 0}}, {"20.05.2021": {"plan": 0, "fact": 0}}, {"21.05.2021": {"plan": 0, "fact": 0}}, {"22.05.2021": {"plan": 0, "fact": 0}}, {"23.05.2021": {"plan": 0, "fact": 0}}, {"24.05.2021": {"plan": 0, "fact": 0}}, {"25.05.2021": {"plan": 0, "fact": 0}}, {"26.05.2021": {"plan": 0, "fact": 0}}, {"27.05.2021": {"plan": 0, "fact": 0}}, {"28.05.2021": {"plan": 0, "fact": 0}}, {"29.05.2021": {"plan": 0, "fact": 0}}, {"30.05.2021": {"plan": 0, "fact": 0}}, {"31.05.2021": {"plan": 1, "fact": 1}}], "comments": null}, "guid": "S88-1770"}, {"work title": "Монтаж кабельных лотков", "work id": "3", "upper works": ["Проект: ОКС 108.17 - Куст-88 ОКС 108.17 - Куст №88. Уровень 4", "WBS: ОКС 108.17 - Куст-88.3.2 Обустройство куста", "WBS: ОКС 108.17 - Куст-88.3.2.1 Подэтап 1", "WBS: ОКС 108.17 - Куст-88.3.2.1.11 Сети автоматизированной системы управления (АК)"], "measurements": "мп", "amount": 454, "work_data": {"start_date": {"plan": "16.11.2019", "estimate": null, "fact": null}, "stop_date": {"plan": "18.05.2020", "estimate": null, "fact": null}, "complite_state_perc": {"plan": 100.0, "fact": 100.0}, "complite_state_value": {"plan": 454, "fact": 454}, "current_remain_perc": null, "current_remain_value": null, "whole_remain_perc": 0, "whole_remain_value": 0, "mounth_complite_perc": {"plan": null, "fact": null}, "mounth_complite_value": {"plan": 0, "fact": 143}, "progress": [{"01.05.2021": {"plan": 0, "fact": 0}}, {"02.05.2021": {"plan": 0, "fact": 0}}, {"03.05.2021": {"plan": 0, "fact": 0}}, {"04.05.2021": {"plan": 0, "fact": 0}}, {"05.05.2021": {"plan": 0, "fact": 0}}, {"06.05.2021": {"plan": 0, "fact": 0}}, {"07.05.2021": {"plan": 0, "fact": 0}}, {"08.05.2021": {"plan": 0, "fact": 0}}, {"09.05.2021": {"plan": 0, "fact": 0}}, {"10.05.2021": {"plan": 0, "fact": 0}}, {"11.05.2021": {"plan": 0, "fact": 0}}, {"12.05.2021": {"plan": 0, "fact": 0}}, {"13.05.2021": {"plan": 0, "fact": 0}}, {"14.05.2021": {"plan": 0, "fact": 0}}, {"15.05.2021": {"plan": 0, "fact": 0}}, {"16.05.2021": {"plan": 0, "fact": 0}}, {"17.05.2021": {"plan": 0, "fact": 0}}, {"18.05.2021": {"plan": 0, "fact": 0}}, {"19.05.2021": {"plan": 0, "fact": 0}}, {"20.05.2021": {"plan": 0, "fact": 0}}, {"21.05.2021": {"plan": 0, "fact": 0}}, {"22.05.2021": {"plan": 0, "fact": 0}}, {"23.05.2021": {"plan": 0, "fact": 0}}, {"24.05.2021": {"plan": 0, "fact": 0}}, {"25.05.2021": {"plan": 0, "fact": 14}}, {"26.05.2021": {"plan": 0, "fact": 30.6}}, {"27.05.2021": {"plan": 0, "fact": 27.3}}, {"28.05.2021": {"plan": 0, "fact": 22.3}}, {"29.05.2021": {"plan": 0, "fact": 22.9}}, {"30.05.2021": {"plan": 0, "fact": 22.9}}, {"31.05.2021": {"plan": 0, "fact": 3}}], "comments": null}, "guid": "S88-1750"}, {"work title": "Монтаж кабельных лотков", "work id": "4", "upper works": ["Проект: ОКС 108.17 - Куст-88 ОКС 108.17 - Куст №88. Уровень 4", "WBS: ОКС 108.17 - Куст-88.3.2 Обустройство куста", "WBS: ОКС 108.17 - Куст-88.3.2.1 Подэтап 1", "WBS: ОКС 108.17 - Куст-88.3.2.1.15 Сети технологической связи (ССР)"], "measurements": "мп", "amount": 16, "work_data": {"start_date": {"plan": "16.11.2019", "estimate": null, "fact": null}, "stop_date": {"plan": "18.05.2020", "estimate": null, "fact": null}, "complite_state_perc": {"plan": 100.0, "fact": 0.0}, "complite_state_value": {"plan": 16, "fact": 0}, "current_remain_perc": 100.0, "current_remain_value": 16, "whole_remain_perc": 100.0, "whole_remain_value": 16, "mounth_complite_perc": {"plan": 100.0, "fact": 0.0}, "mounth_complite_value": {"plan": 16, "fact": 0}, "progress": [{"01.05.2021": {"plan": 0, "fact": 0}}, {"02.05.2021": {"plan": 10, "fact": 0}}, {"03.05.2021": {"plan": 6, "fact": 0}}, {"04.05.2021": {"plan": 0, "fact": 0}}, {"05.05.2021": {"plan": 0, "fact": 0}}, {"06.05.2021": {"plan": 0, "fact": 0}}, {"07.05.2021": {"plan": 0, "fact": 0}}, {"08.05.2021": {"plan": 0, "fact": 0}}, {"09.05.2021": {"plan": 0, "fact": 0}}, {"10.05.2021": {"plan": 0, "fact": 0}}, {"11.05.2021": {"plan": 0, "fact": 0}}, {"12.05.2021": {"plan": 0, "fact": 0}}, {"13.05.2021": {"plan": 0, "fact": 0}}, {"14.05.2021": {"plan": 0, "fact": 0}}, {"15.05.2021": {"plan": 0, "fact": 0}}, {"16.05.2021": {"plan": 0, "fact": 0}}, {"17.05.2021": {"plan": 0, "fact": 0}}, {"18.05.2021": {"plan": 0, "fact": 0}}, {"19.05.2021": {"plan": 0, "fact": 0}}, {"20.05.2021": {"plan": 0, "fact": 0}}, {"21.05.2021": {"plan": 0, "fact": 0}}, {"22.05.2021": {"plan": 0, "fact": 0}}, {"23.05.2021": {"plan": 0, "fact": 0}}, {"24.05.2021": {"plan": 0, "fact": 0}}, {"25.05.2021": {"plan": 0, "fact": 0}}, {"26.05.2021": {"plan": 0, "fact": 0}}, {"27.05.2021": {"plan": 0, "fact": 0}}, {"28.05.2021": {"plan": 0, "fact": 0}}, {"29.05.2021": {"plan": 0, "fact": 0}}, {"30.05.2021": {"plan": 0, "fact": 0}}, {"31.05.2021": {"plan": 0, "fact": 0}}], "comments": null}, "guid": "S88-1750"}, {"work title": "Укладка полосового заземления", "work id": "5", "upper works": ["Проект: ОКС 108.17 - Куст-88 ОКС 108.17 - Куст №88. Уровень 4", "WBS: ОКС 108.17 - Куст-88.3.2 Обустройство куста", "WBS: ОКС 108.17 - Куст-88.3.2.1 Подэтап 1", "WBS: ОКС 108.17 - Куст-88.3.2.2.4 Электрические сети (ЭС)"], "measurements": "мп", "amount": 30, "work_data": {"start_date": {"plan": "15.11.2019", "estimate": null, "fact": null}, "stop_date": {"plan": "05.05.2020", "estimate": null, "fact": null}, "complite_state_perc": {"plan": 100.0, "fact": 0.0}, "complite_state_value": {"plan": 30, "fact": 0}, "current_remain_perc": 100.0, "current_remain_value": 30, "whole_remain_perc": 100.0, "whole_remain_value": 30, "mounth_complite_perc": {"plan": 100.0, "fact": 0.0}, "mounth_complite_value": {"plan": 30, "fact": 0}, "progress": [{"01.05.2021": {"plan": 0, "fact": 0}}, {"02.05.2021": {"plan": 0, "fact": 0}}, {"03.05.2021": {"plan": 0, "fact": 0}}, {"04.05.2021": {"plan": 0, "fact": 0}}, {"05.05.2021": {"plan": 0, "fact": 0}}, {"06.05.2021": {"plan": 0, "fact": 0}}, {"07.05.2021": {"plan": 0, "fact": 0}}, {"08.05.2021": {"plan": 0, "fact": 0}}, {"09.05.2021": {"plan": 0, "fact": 0}}, {"10.05.2021": {"plan": 0, "fact": 0}}, {"11.05.2021": {"plan": 0, "fact": 0}}, {"12.05.2021": {"plan": 0, "fact": 0}}, {"13.05.2021": {"plan": 0, "fact": 0}}, {"14.05.2021": {"plan": 0, "fact": 0}}, {"15.05.2021": {"plan": 0, "fact": 0}}, {"16.05.2021": {"plan": 0, "fact": 0}}, {"17.05.2021": {"plan": 0, "fact": 0}}, {"18.05.2021": {"plan": 0, "fact": 0}}, {"19.05.2021": {"plan": 0, "fact": 0}}, {"20.05.2021": {"plan": 10, "fact": 0}}, {"21.05.2021": {"plan": 10, "fact": 0}}, {"22.05.2021": {"plan": 10, "fact": 0}}, {"23.05.2021": {"plan": 0, "fact": 0}}, {"24.05.2021": {"plan": 0, "fact": 0}}, {"25.05.2021": {"plan": 0, "fact": 0}}, {"26.05.2021": {"plan": 0, "fact": 0}}, {"27.05.2021": {"plan": 0, "fact": 0}}, {"28.05.2021": {"plan": 0, "fact": 0}}, {"29.05.2021": {"plan": 0, "fact": 0}}, {"30.05.2021": {"plan": 0, "fact": 0}}, {"31.05.2021": {"plan": 0, "fact": 0}}], "comments": null}, "guid": "S88-27560"}, {"work title": "Монтаж приборов АСУТП", "work id": "6", "upper works": ["Проект: ОКС 108.17 - Куст-88 ОКС 108.17 - Куст №88. Уровень 4", "WBS: ОКС 108.17 - Куст-88.3.2 Обустройство куста", "WBS: ОКС 108.17 - Куст-88.3.2.1 Подэтап 1", "WBS: ОКС 108.17 - Куст-88.3.2.2.6 Сети автоматизированной системы управления (АК)"], "measurements": "шт", "amount": 48, "work_data": {"start_date": {"plan": "24.10.2019", "estimate": null, "fact": null}, "stop_date": {"plan": "20.05.2020", "estimate": null, "fact": null}, "complite_state_perc": {"plan": 100.0, "fact": 47.91666666666667}, "complite_state_value": {"plan": 48, "fact": 23}, "current_remain_perc": 0, "current_remain_value": 0, "whole_remain_perc": 52.08333333333333, "whole_remain_value": 25, "mounth_complite_perc": {"plan": 100.0, "fact": 153.33333333333334}, "mounth_complite_value": {"plan": 15, "fact": 23}, "progress": [{"01.05.2021": {"plan": 0, "fact": 0}}, {"02.05.2021": {"plan": 0, "fact": 0}}, {"03.05.2021": {"plan": 0, "fact": 0}}, {"04.05.2021": {"plan": 0, "fact": 0}}, {"05.05.2021": {"plan": 2, "fact": 0}}, {"06.05.2021": {"plan": 2, "fact": 0}}, {"07.05.2021": {"plan": 2, "fact": 0}}, {"08.05.2021": {"plan": 2, "fact": 0}}, {"09.05.2021": {"plan": 2, "fact": 0}}, {"10.05.2021": {"plan": 2, "fact": 0}}, {"11.05.2021": {"plan": 2, "fact": 0}}, {"12.05.2021": {"plan": 1, "fact": 0}}, {"13.05.2021": {"plan": 0, "fact": 0}}, {"14.05.2021": {"plan": 0, "fact": 0}}, {"15.05.2021": {"plan": 0, "fact": 0}}, {"16.05.2021": {"plan": 0, "fact": 0}}, {"17.05.2021": {"plan": 0, "fact": 0}}, {"18.05.2021": {"plan": 0, "fact": 0}}, {"19.05.2021": {"plan": 0, "fact": 0}}, {"20.05.2021": {"plan": 0, "fact": 0}}, {"21.05.2021": {"plan": 0, "fact": 0}}, {"22.05.2021": {"plan": 0, "fact": 0}}, {"23.05.2021": {"plan": 0, "fact": 0}}, {"24.05.2021": {"plan": 0, "fact": 0}}, {"25.05.2021": {"plan": 0, "fact": 0}}, {"26.05.2021": {"plan": 0, "fact": 0}}, {"27.05.2021": {"plan": 0, "fact": 17}}, {"28.05.2021": {"plan": 0, "fact": 0}}, {"29.05.2021": {"plan": 0, "fact": 0}}, {"30.05.2021": {"plan": 0, "fact": 0}}, {"31.05.2021": {"plan": 0, "fact": 6}}], "comments": null}, "guid": "S88-1770"}, {"work title": "Монтаж кабеля АСУТП", "work id": "7", "upper works": ["Проект: ОКС 108.17 - Куст-88 ОКС 108.17 - Куст №88. Уровень 4", "WBS: ОКС 108.17 - Куст-88.3.2 Обустройство куста", "WBS: ОКС 108.17 - Куст-88.3.2.1 Подэтап 1", "WBS: ОКС 108.17 - Куст-88.3.2.2.6 Сети автоматизированной системы управления (АК)"], "measurements": "мп", "amount": 2532, "work_data": {"start_date": {"plan": "23.10.2019", "estimate": null, "fact": null}, "stop_date": {"plan": "20.05.2020", "estimate": null, "fact": null}, "complite_state_perc": {"plan": 100.0, "fact": 90.20537124802527}, "complite_state_value": {"plan": 2532, "fact": 2284}, "current_remain_perc": 93.58490566037736, "current_remain_value": 248, "whole_remain_perc": 9.794628751974727, "whole_remain_value": 248, "mounth_complite_perc": {"plan": 100.0, "fact": 6.415094339622642}, "mounth_complite_value": {"plan": 265, "fact": 17}, "progress": [{"01.05.2021": {"plan": 50, "fact": 17}}, {"02.05.2021": {"plan": 50, "fact": 0}}, {"03.05.2021": {"plan": 55, "fact": 0}}, {"04.05.2021": {"plan": 55, "fact": 0}}, {"05.05.2021": {"plan": 55, "fact": 0}}, {"06.05.2021": {"plan": 0, "fact": 0}}, {"07.05.2021": {"plan": 0, "fact": 0}}, {"08.05.2021": {"plan": 0, "fact": 0}}, {"09.05.2021": {"plan": 0, "fact": 0}}, {"10.05.2021": {"plan": 0, "fact": 0}}, {"11.05.2021": {"plan": 0, "fact": 0}}, {"12.05.2021": {"plan": 0, "fact": 0}}, {"13.05.2021": {"plan": 0, "fact": 0}}, {"14.05.2021": {"plan": 0, "fact": 0}}, {"15.05.2021": {"plan": 0, "fact": 0}}, {"16.05.2021": {"plan": 0, "fact": 0}}, {"17.05.2021": {"plan": 0, "fact": 0}}, {"18.05.2021": {"plan": 0, "fact": 0}}, {"19.05.2021": {"plan": 0, "fact": 0}}, {"20.05.2021": {"plan": 0, "fact": 0}}, {"21.05.2021": {"plan": 0, "fact": 0}}, {"22.05.2021": {"plan": 0, "fact": 0}}, {"23.05.2021": {"plan": 0, "fact": 0}}, {"24.05.2021": {"plan": 0, "fact": 0}}, {"25.05.2021": {"plan": 0, "fact": 0}}, {"26.05.2021": {"plan": 0, "fact": 0}}, {"27.05.2021": {"plan": 0, "fact": 0}}, {"28.05.2021": {"plan": 0, "fact": 0}}, {"29.05.2021": {"plan": 0, "fact": 0}}, {"30.05.2021": {"plan": 0, "fact": 0}}, {"31.05.2021": {"plan": 0, "fact": 0}}], "comments": null}, "guid": "S88-2420"}], "resource": [{"resource_id": null, "resource_name": "ИТР (инженерно-технический персонал)", "type": "human", "progress": [{"01.05.2021": {"plan": 1, "fact": 1}}, {"02.05.2021": {"plan": 1, "fact": 1}}, {"03.05.2021": {"plan": 1, "fact": 1}}, {"04.05.2021": {"plan": 1, "fact": 1}}, {"05.05.2021": {"plan": 1, "fact": 1}}, {"06.05.2021": {"plan": 1, "fact": 1}}, {"07.05.2021": {"plan": 1, "fact": 0}}, {"08.05.2021": {"plan": 1, "fact": 1}}, {"09.05.2021": {"plan": 1, "fact": 0}}, {"10.05.2021": {"plan": 1, "fact": 0}}, {"11.05.2021": {"plan": 1, "fact": 0}}, {"12.05.2021": {"plan": 1, "fact": 0}}, {"13.05.2021": {"plan": 1, "fact": 0}}, {"14.05.2021": {"plan": 1, "fact": 0}}, {"15.05.2021": {"plan": 1, "fact": 0}}, {"16.05.2021": {"plan": 1, "fact": 0}}, {"17.05.2021": {"plan": 1, "fact": 0}}, {"18.05.2021": {"plan": 1, "fact": 0}}, {"19.05.2021": {"plan": 1, "fact": 0}}, {"20.05.2021": {"plan": 1, "fact": 0}}, {"21.05.2021": {"plan": 1, "fact": 1}}, {"22.05.2021": {"plan": 1, "fact": 1}}, {"23.05.2021": {"plan": 1, "fact": 1}}, {"24.05.2021": {"plan": 1, "fact": 1}}, {"25.05.2021": {"plan": 1, "fact": 1}}, {"26.05.2021": {"plan": 1, "fact": 1}}, {"27.05.2021": {"plan": 1, "fact": 1}}, {"28.05.2021": {"plan": 1, "fact": 1}}, {"29.05.2021": {"plan": 1, "fact": 1}}, {"30.05.2021": {"plan": 1, "fact": 1}}, {"31.05.2021": {"plan": 1, "fact": 1}}], "comments": null}, {"resource_id": null, "resource_name": "Автомеханик", "type": "human", "progress": [{"01.05.2021": {"plan": 0, "fact": 0}}, {"02.05.2021": {"plan": 0, "fact": 0}}, {"03.05.2021": {"plan": 0, "fact": 0}}, {"04.05.2021": {"plan": 0, "fact": 0}}, {"05.05.2021": {"plan": 0, "fact": 0}}, {"06.05.2021": {"plan": 0, "fact": 0}}, {"07.05.2021": {"plan": 0, "fact": 0}}, {"08.05.2021": {"plan": 0, "fact": 0}}, {"09.05.2021": {"plan": 0, "fact": 0}}, {"10.05.2021": {"plan": 0, "fact": 0}}, {"11.05.2021": {"plan": 0, "fact": 0}}, {"12.05.2021": {"plan": 0, "fact": 0}}, {"13.05.2021": {"plan": 0, "fact": 0}}, {"14.05.2021": {"plan": 0, "fact": 0}}, {"15.05.2021": {"plan": 0, "fact": 0}}, {"16.05.2021": {"plan": 0, "fact": 0}}, {"17.05.2021": {"plan": 0, "fact": 0}}, {"18.05.2021": {"plan": 0, "fact": 0}}, {"19.05.2021": {"plan": 0, "fact": 0}}, {"20.05.2021": {"plan": 0, "fact": 0}}, {"21.05.2021": {"plan": 0, "fact": 0}}, {"22.05.2021": {"plan": 0, "fact": 0}}, {"23.05.2021": {"plan": 0, "fact": 0}}, {"24.05.2021": {"plan": 0, "fact": 0}}, {"25.05.2021": {"plan": 0, "fact": 0}}, {"26.05.2021": {"plan": 0, "fact": 0}}, {"27.05.2021": {"plan": 0, "fact": 0}}, {"28.05.2021": {"plan": 0, "fact": 0}}, {"29.05.2021": {"plan": 0, "fact": 0}}, {"30.05.2021": {"plan": 0, "fact": 0}}, {"31.05.2021": {"plan": 0, "fact": 0}}], "comments": null}, {"resource_id": null, "resource_name": "Бурильщик, помошник бурильщика", "type": "human", "progress": [{"01.05.2021": {"plan": 0, "fact": 0}}, {"02.05.2021": {"plan": 0, "fact": 0}}, {"03.05.2021": {"plan": 0, "fact": 0}}, {"04.05.2021": {"plan": 0, "fact": 0}}, {"05.05.2021": {"plan": 0, "fact": 0}}, {"06.05.2021": {"plan": 0, "fact": 0}}, {"07.05.2021": {"plan": 0, "fact": 0}}, {"08.05.2021": {"plan": 0, "fact": 0}}, {"09.05.2021": {"plan": 0, "fact": 0}}, {"10.05.2021": {"plan": 0, "fact": 0}}, {"11.05.2021": {"plan": 0, "fact": 0}}, {"12.05.2021": {"plan": 0, "fact": 0}}, {"13.05.2021": {"plan": 0, "fact": 0}}, {"14.05.2021": {"plan": 0, "fact": 0}}, {"15.05.2021": {"plan": 0, "fact": 0}}, {"16.05.2021": {"plan": 0, "fact": 0}}, {"17.05.2021": {"plan": 0, "fact": 0}}, {"18.05.2021": {"plan": 0, "fact": 0}}, {"19.05.2021": {"plan": 0, "fact": 0}}, {"20.05.2021": {"plan": 0, "fact": 0}}, {"21.05.2021": {"plan": 0, "fact": 0}}, {"22.05.2021": {"plan": 0, "fact": 0}}, {"23.05.2021": {"plan": 0, "fact": 0}}, {"24.05.2021": {"plan": 0, "fact": 0}}, {"25.05.2021": {"plan": 0, "fact": 0}}, {"26.05.2021": {"plan": 0, "fact": 0}}, {"27.05.2021": {"plan": 0, "fact": 0}}, {"28.05.2021": {"plan": 0, "fact": 0}}, {"29.05.2021": {"plan": 0, "fact": 0}}, {"30.05.2021": {"plan": 0, "fact": 0}}, {"31.05.2021": {"plan": 0, "fact": 0}}], "comments": null}, {"resource_id": null, "resource_name": "Вентиляционщик", "type": "human", "progress": [{"01.05.2021": {"plan": 0, "fact": 0}}, {"02.05.2021": {"plan": 0, "fact": 0}}, {"03.05.2021": {"plan": 0, "fact": 0}}, {"04.05.2021": {"plan": 0, "fact": 0}}, {"05.05.2021": {"plan": 0, "fact": 0}}, {"06.05.2021": {"plan": 0, "fact": 0}}, {"07.05.2021": {"plan": 0, "fact": 0}}, {"08.05.2021": {"plan": 0, "fact": 0}}, {"09.05.2021": {"plan": 0, "fact": 0}}, {"10.05.2021": {"plan": 0, "fact": 0}}, {"11.05.2021": {"plan": 0, "fact": 0}}, {"12.05.2021": {"plan": 0, "fact": 0}}, {"13.05.2021": {"plan": 0, "fact": 0}}, {"14.05.2021": {"plan": 0, "fact": 0}}, {"15.05.2021": {"plan": 0, "fact": 0}}, {"16.05.2021": {"plan": 0, "fact": 0}}, {"17.05.2021": {"plan": 0, "fact": 0}}, {"18.05.2021": {"plan": 0, "fact": 0}}, {"19.05.2021": {"plan": 0, "fact": 0}}, {"20.05.2021": {"plan": 0, "fact": 0}}, {"21.05.2021": {"plan": 0, "fact": 0}}, {"22.05.2021": {"plan": 0, "fact": 0}}, {"23.05.2021": {"plan": 0, "fact": 0}}, {"24.05.2021": {"plan": 0, "fact": 0}}, {"25.05.2021": {"plan": 0, "fact": 0}}, {"26.05.2021": {"plan": 0, "fact": 0}}, {"27.05.2021": {"plan": 0, "fact": 0}}, {"28.05.2021": {"plan": 0, "fact": 0}}, {"29.05.2021": {"plan": 0, "fact": 0}}, {"30.05.2021": {"plan": 0, "fact": 0}}, {"31.05.2021": {"plan": 0, "fact": 0}}], "comments": null}, {"resource_id": null, "resource_name": "Геодезист", "type": "human", "progress": [{"01.05.2021": {"plan": 0, "fact": 0}}, {"02.05.2021": {"plan": 0, "fact": 0}}, {"03.05.2021": {"plan": 0, "fact": 0}}, {"04.05.2021": {"plan": 0, "fact": 0}}, {"05.05.2021": {"plan": 0, "fact": 0}}, {"06.05.2021": {"plan": 0, "fact": 0}}, {"07.05.2021": {"plan": 0, "fact": 0}}, {"08.05.2021": {"plan": 0, "fact": 0}}, {"09.05.2021": {"plan": 0, "fact": 0}}, {"10.05.2021": {"plan": 0, "fact": 0}}, {"11.05.2021": {"plan": 0, "fact": 0}}, {"12.05.2021": {"plan": 0, "fact": 0}}, {"13.05.2021": {"plan": 0, "fact": 0}}, {"14.05.2021": {"plan": 0, "fact": 0}}, {"15.05.2021": {"plan": 0, "fact": 0}}, {"16.05.2021": {"plan": 0, "fact": 0}}, {"17.05.2021": {"plan": 0, "fact": 0}}, {"18.05.2021": {"plan": 0, "fact": 0}}, {"19.05.2021": {"plan": 0, "fact": 0}}, {"20.05.2021": {"plan": 0, "fact": 0}}, {"21.05.2021": {"plan": 0, "fact": 0}}, {"22.05.2021": {"plan": 0, "fact": 0}}, {"23.05.2021": {"plan": 0, "fact": 0}}, {"24.05.2021": {"plan": 0, "fact": 0}}, {"25.05.2021": {"plan": 0, "fact": 0}}, {"26.05.2021": {"plan": 0, "fact": 0}}, {"27.05.2021": {"plan": 0, "fact": 0}}, {"28.05.2021": {"plan": 0, "fact": 0}}, {"29.05.2021": {"plan": 0, "fact": 0}}, {"30.05.2021": {"plan": 0, "fact": 0}}, {"31.05.2021": {"plan": 0, "fact": 0}}], "comments": null}, {"resource_id": null, "resource_name": "Деффектоскопист", "type": "human", "progress": [{"01.05.2021": {"plan": 0, "fact": 0}}, {"02.05.2021": {"plan": 0, "fact": 0}}, {"03.05.2021": {"plan": 0, "fact": 0}}, {"04.05.2021": {"plan": 0, "fact": 0}}, {"05.05.2021": {"plan": 0, "fact": 0}}, {"06.05.2021": {"plan": 0, "fact": 0}}, {"07.05.2021": {"plan": 0, "fact": 0}}, {"08.05.2021": {"plan": 0, "fact": 0}}, {"09.05.2021": {"plan": 0, "fact": 0}}, {"10.05.2021": {"plan": 0, "fact": 0}}, {"11.05.2021": {"plan": 0, "fact": 0}}, {"12.05.2021": {"plan": 0, "fact": 0}}, {"13.05.2021": {"plan": 0, "fact": 0}}, {"14.05.2021": {"plan": 0, "fact": 0}}, {"15.05.2021": {"plan": 0, "fact": 0}}, {"16.05.2021": {"plan": 0, "fact": 0}}, {"17.05.2021": {"plan": 0, "fact": 0}}, {"18.05.2021": {"plan": 0, "fact": 0}}, {"19.05.2021": {"plan": 0, "fact": 0}}, {"20.05.2021": {"plan": 0, "fact": 0}}, {"21.05.2021": {"plan": 0, "fact": 0}}, {"22.05.2021": {"plan": 0, "fact": 0}}, {"23.05.2021": {"plan": 0, "fact": 0}}, {"24.05.2021": {"plan": 0, "fact": 0}}, {"25.05.2021": {"plan": 0, "fact": 0}}, {"26.05.2021": {"plan": 0, "fact": 0}}, {"27.05.2021": {"plan": 0, "fact": 0}}, {"28.05.2021": {"plan": 0, "fact": 0}}, {"29.05.2021": {"plan": 0, "fact": 0}}, {"30.05.2021": {"plan": 0, "fact": 0}}, {"31.05.2021": {"plan": 0, "fact": 0}}], "comments": null}, {"resource_id": null, "resource_name": "Изолировщик", "type": "human", "progress": [{"01.05.2021": {"plan": 0, "fact": 0}}, {"02.05.2021": {"plan": 0, "fact": 0}}, {"03.05.2021": {"plan": 0, "fact": 0}}, {"04.05.2021": {"plan": 0, "fact": 0}}, {"05.05.2021": {"plan": 0, "fact": 0}}, {"06.05.2021": {"plan": 0, "fact": 0}}, {"07.05.2021": {"plan": 0, "fact": 0}}, {"08.05.2021": {"plan": 0, "fact": 0}}, {"09.05.2021": {"plan": 0, "fact": 0}}, {"10.05.2021": {"plan": 0, "fact": 0}}, {"11.05.2021": {"plan": 0, "fact": 0}}, {"12.05.2021": {"plan": 0, "fact": 0}}, {"13.05.2021": {"plan": 0, "fact": 0}}, {"14.05.2021": {"plan": 0, "fact": 0}}, {"15.05.2021": {"plan": 0, "fact": 0}}, {"16.05.2021": {"plan": 0, "fact": 0}}, {"17.05.2021": {"plan": 0, "fact": 0}}, {"18.05.2021": {"plan": 0, "fact": 0}}, {"19.05.2021": {"plan": 0, "fact": 0}}, {"20.05.2021": {"plan": 0, "fact": 0}}, {"21.05.2021": {"plan": 0, "fact": 0}}, {"22.05.2021": {"plan": 0, "fact": 0}}, {"23.05.2021": {"plan": 0, "fact": 0}}, {"24.05.2021": {"plan": 0, "fact": 0}}, {"25.05.2021": {"plan": 0, "fact": 0}}, {"26.05.2021": {"plan": 0, "fact": 0}}, {"27.05.2021": {"plan": 0, "fact": 0}}, {"28.05.2021": {"plan": 0, "fact": 0}}, {"29.05.2021": {"plan": 0, "fact": 0}}, {"30.05.2021": {"plan": 0, "fact": 0}}, {"31.05.2021": {"plan": 0, "fact": 0}}], "comments": null}, {"resource_id": null, "resource_name": "Кровельщик", "type": "human", "progress": [{"01.05.2021": {"plan": 0, "fact": 0}}, {"02.05.2021": {"plan": 0, "fact": 0}}, {"03.05.2021": {"plan": 0, "fact": 0}}, {"04.05.2021": {"plan": 0, "fact": 0}}, {"05.05.2021": {"plan": 0, "fact": 0}}, {"06.05.2021": {"plan": 0, "fact": 0}}, {"07.05.2021": {"plan": 0, "fact": 0}}, {"08.05.2021": {"plan": 0, "fact": 0}}, {"09.05.2021": {"plan": 0, "fact": 0}}, {"10.05.2021": {"plan": 0, "fact": 0}}, {"11.05.2021": {"plan": 0, "fact": 0}}, {"12.05.2021": {"plan": 0, "fact": 0}}, {"13.05.2021": {"plan": 0, "fact": 0}}, {"14.05.2021": {"plan": 0, "fact": 0}}, {"15.05.2021": {"plan": 0, "fact": 0}}, {"16.05.2021": {"plan": 0, "fact": 0}}, {"17.05.2021": {"plan": 0, "fact": 0}}, {"18.05.2021": {"plan": 0, "fact": 0}}, {"19.05.2021": {"plan": 0, "fact": 0}}, {"20.05.2021": {"plan": 0, "fact": 0}}, {"21.05.2021": {"plan": 0, "fact": 0}}, {"22.05.2021": {"plan": 0, "fact": 0}}, {"23.05.2021": {"plan": 0, "fact": 0}}, {"24.05.2021": {"plan": 0, "fact": 0}}, {"25.05.2021": {"plan": 0, "fact": 0}}, {"26.05.2021": {"plan": 0, "fact": 0}}, {"27.05.2021": {"plan": 0, "fact": 0}}, {"28.05.2021": {"plan": 0, "fact": 0}}, {"29.05.2021": {"plan": 0, "fact": 0}}, {"30.05.2021": {"plan": 0, "fact": 0}}, {"31.05.2021": {"plan": 0, "fact": 0}}], "comments": null}, {"resource_id": null, "resource_name": "Маляр", "type": "human", "progress": [{"01.05.2021": {"plan": 0, "fact": 0}}, {"02.05.2021": {"plan": 0, "fact": 0}}, {"03.05.2021": {"plan": 0, "fact": 0}}, {"04.05.2021": {"plan": 0, "fact": 0}}, {"05.05.2021": {"plan": 0, "fact": 0}}, {"06.05.2021": {"plan": 0, "fact": 0}}, {"07.05.2021": {"plan": 0, "fact": 0}}, {"08.05.2021": {"plan": 0, "fact": 0}}, {"09.05.2021": {"plan": 0, "fact": 0}}, {"10.05.2021": {"plan": 0, "fact": 0}}, {"11.05.2021": {"plan": 0, "fact": 0}}, {"12.05.2021": {"plan": 0, "fact": 0}}, {"13.05.2021": {"plan": 0, "fact": 0}}, {"14.05.2021": {"plan": 0, "fact": 0}}, {"15.05.2021": {"plan": 0, "fact": 0}}, {"16.05.2021": {"plan": 0, "fact": 0}}, {"17.05.2021": {"plan": 0, "fact": 0}}, {"18.05.2021": {"plan": 0, "fact": 0}}, {"19.05.2021": {"plan": 0, "fact": 0}}, {"20.05.2021": {"plan": 0, "fact": 0}}, {"21.05.2021": {"plan": 0, "fact": 0}}, {"22.05.2021": {"plan": 0, "fact": 0}}, {"23.05.2021": {"plan": 0, "fact": 0}}, {"24.05.2021": {"plan": 0, "fact": 0}}, {"25.05.2021": {"plan": 0, "fact": 0}}, {"26.05.2021": {"plan": 0, "fact": 0}}, {"27.05.2021": {"plan": 0, "fact": 0}}, {"28.05.2021": {"plan": 0, "fact": 0}}, {"29.05.2021": {"plan": 0, "fact": 0}}, {"30.05.2021": {"plan": 0, "fact": 0}}, {"31.05.2021": {"plan": 0, "fact": 0}}], "comments": null}, {"resource_id": null, "resource_name": "Машинист, водители", "type": "human", "progress": [{"01.05.2021": {"plan": 1, "fact": 1}}, {"02.05.2021": {"plan": 1, "fact": 1}}, {"03.05.2021": {"plan": 1, "fact": 1}}, {"04.05.2021": {"plan": 1, "fact": 1}}, {"05.05.2021": {"plan": 1, "fact": 1}}, {"06.05.2021": {"plan": 1, "fact": 1}}, {"07.05.2021": {"plan": 1, "fact": 0}}, {"08.05.2021": {"plan": 1, "fact": 1}}, {"09.05.2021": {"plan": 1, "fact": 0}}, {"10.05.2021": {"plan": 1, "fact": 0}}, {"11.05.2021": {"plan": 1, "fact": 0}}, {"12.05.2021": {"plan": 1, "fact": 0}}, {"13.05.2021": {"plan": 1, "fact": 0}}, {"14.05.2021": {"plan": 1, "fact": 0}}, {"15.05.2021": {"plan": 1, "fact": 0}}, {"16.05.2021": {"plan": 1, "fact": 0}}, {"17.05.2021": {"plan": 1, "fact": 0}}, {"18.05.2021": {"plan": 1, "fact": 0}}, {"19.05.2021": {"plan": 1, "fact": 0}}, {"20.05.2021": {"plan": 1, "fact": 0}}, {"21.05.2021": {"plan": 1, "fact": 1}}, {"22.05.2021": {"plan": 1, "fact": 1}}, {"23.05.2021": {"plan": 1, "fact": 1}}, {"24.05.2021": {"plan": 1, "fact": 1}}, {"25.05.2021": {"plan": 1, "fact": 1}}, {"26.05.2021": {"plan": 1, "fact": 1}}, {"27.05.2021": {"plan": 1, "fact": 1}}, {"28.05.2021": {"plan": 1, "fact": 1}}, {"29.05.2021": {"plan": 1, "fact": 1}}, {"30.05.2021": {"plan": 1, "fact": 1}}, {"31.05.2021": {"plan": 1, "fact": 1}}], "comments": null}, {"resource_id": null, "resource_name": "Механизатор", "type": "human", "progress": [{"01.05.2021": {"plan": 0, "fact": 0}}, {"02.05.2021": {"plan": 0, "fact": 0}}, {"03.05.2021": {"plan": 0, "fact": 0}}, {"04.05.2021": {"plan": 0, "fact": 0}}, {"05.05.2021": {"plan": 0, "fact": 0}}, {"06.05.2021": {"plan": 0, "fact": 0}}, {"07.05.2021": {"plan": 0, "fact": 0}}, {"08.05.2021": {"plan": 0, "fact": 0}}, {"09.05.2021": {"plan": 0, "fact": 0}}, {"10.05.2021": {"plan": 0, "fact": 0}}, {"11.05.2021": {"plan": 0, "fact": 0}}, {"12.05.2021": {"plan": 0, "fact": 0}}, {"13.05.2021": {"plan": 0, "fact": 0}}, {"14.05.2021": {"plan": 0, "fact": 0}}, {"15.05.2021": {"plan": 0, "fact": 0}}, {"16.05.2021": {"plan": 0, "fact": 0}}, {"17.05.2021": {"plan": 0, "fact": 0}}, {"18.05.2021": {"plan": 0, "fact": 0}}, {"19.05.2021": {"plan": 0, "fact": 0}}, {"20.05.2021": {"plan": 0, "fact": 0}}, {"21.05.2021": {"plan": 0, "fact": 0}}, {"22.05.2021": {"plan": 0, "fact": 0}}, {"23.05.2021": {"plan": 0, "fact": 0}}, {"24.05.2021": {"plan": 0, "fact": 0}}, {"25.05.2021": {"plan": 0, "fact": 0}}, {"26.05.2021": {"plan": 0, "fact": 0}}, {"27.05.2021": {"plan": 0, "fact": 0}}, {"28.05.2021": {"plan": 0, "fact": 0}}, {"29.05.2021": {"plan": 0, "fact": 0}}, {"30.05.2021": {"plan": 0, "fact": 0}}, {"31.05.2021": {"plan": 0, "fact": 0}}], "comments": null}, {"resource_id": null, "resource_name": "Монтажник МК (металлоконструкций)", "type": "human", "progress": [{"01.05.2021": {"plan": 0, "fact": 0}}, {"02.05.2021": {"plan": 0, "fact": 0}}, {"03.05.2021": {"plan": 0, "fact": 0}}, {"04.05.2021": {"plan": 0, "fact": 0}}, {"05.05.2021": {"plan": 0, "fact": 0}}, {"06.05.2021": {"plan": 0, "fact": 0}}, {"07.05.2021": {"plan": 0, "fact": 0}}, {"08.05.2021": {"plan": 0, "fact": 0}}, {"09.05.2021": {"plan": 0, "fact": 0}}, {"10.05.2021": {"plan": 0, "fact": 0}}, {"11.05.2021": {"plan": 0, "fact": 0}}, {"12.05.2021": {"plan": 0, "fact": 0}}, {"13.05.2021": {"plan": 0, "fact": 0}}, {"14.05.2021": {"plan": 0, "fact": 0}}, {"15.05.2021": {"plan": 0, "fact": 0}}, {"16.05.2021": {"plan": 0, "fact": 0}}, {"17.05.2021": {"plan": 0, "fact": 0}}, {"18.05.2021": {"plan": 0, "fact": 0}}, {"19.05.2021": {"plan": 0, "fact": 0}}, {"20.05.2021": {"plan": 0, "fact": 0}}, {"21.05.2021": {"plan": 0, "fact": 0}}, {"22.05.2021": {"plan": 0, "fact": 0}}, {"23.05.2021": {"plan": 0, "fact": 0}}, {"24.05.2021": {"plan": 0, "fact": 0}}, {"25.05.2021": {"plan": 0, "fact": 0}}, {"26.05.2021": {"plan": 0, "fact": 0}}, {"27.05.2021": {"plan": 0, "fact": 0}}, {"28.05.2021": {"plan": 0, "fact": 0}}, {"29.05.2021": {"plan": 0, "fact": 0}}, {"30.05.2021": {"plan": 0, "fact": 0}}, {"31.05.2021": {"plan": 0, "fact": 0}}], "comments": null}, {"resource_id": null, "resource_name": "Монтажник ТТ (технологических трубопроводов)", "type": "human", "progress": [{"01.05.2021": {"plan": 0, "fact": 0}}, {"02.05.2021": {"plan": 0, "fact": 0}}, {"03.05.2021": {"plan": 0, "fact": 0}}, {"04.05.2021": {"plan": 0, "fact": 0}}, {"05.05.2021": {"plan": 0, "fact": 0}}, {"06.05.2021": {"plan": 0, "fact": 2}}, {"07.05.2021": {"plan": 0, "fact": 0}}, {"08.05.2021": {"plan": 0, "fact": 0}}, {"09.05.2021": {"plan": 0, "fact": 0}}, {"10.05.2021": {"plan": 0, "fact": 0}}, {"11.05.2021": {"plan": 0, "fact": 0}}, {"12.05.2021": {"plan": 0, "fact": 0}}, {"13.05.2021": {"plan": 0, "fact": 0}}, {"14.05.2021": {"plan": 0, "fact": 0}}, {"15.05.2021": {"plan": 0, "fact": 0}}, {"16.05.2021": {"plan": 0, "fact": 0}}, {"17.05.2021": {"plan": 0, "fact": 0}}, {"18.05.2021": {"plan": 0, "fact": 0}}, {"19.05.2021": {"plan": 0, "fact": 0}}, {"20.05.2021": {"plan": 0, "fact": 0}}, {"21.05.2021": {"plan": 0, "fact": 0}}, {"22.05.2021": {"plan": 0, "fact": 0}}, {"23.05.2021": {"plan": 0, "fact": 0}}, {"24.05.2021": {"plan": 0, "fact": 0}}, {"25.05.2021": {"plan": 0, "fact": 0}}, {"26.05.2021": {"plan": 0, "fact": 0}}, {"27.05.2021": {"plan": 0, "fact": 0}}, {"28.05.2021": {"plan": 0, "fact": 0}}, {"29.05.2021": {"plan": 0, "fact": 0}}, {"30.05.2021": {"plan": 0, "fact": 0}}, {"31.05.2021": {"plan": 0, "fact": 0}}], "comments": null}, {"resource_id": null, "resource_name": "Наладчик", "type": "human", "progress": [{"01.05.2021": {"plan": 0, "fact": 0}}, {"02.05.2021": {"plan": 0, "fact": 0}}, {"03.05.2021": {"plan": 0, "fact": 0}}, {"04.05.2021": {"plan": 0, "fact": 0}}, {"05.05.2021": {"plan": 0, "fact": 0}}, {"06.05.2021": {"plan": 0, "fact": 0}}, {"07.05.2021": {"plan": 0, "fact": 0}}, {"08.05.2021": {"plan": 0, "fact": 0}}, {"09.05.2021": {"plan": 0, "fact": 0}}, {"10.05.2021": {"plan": 0, "fact": 0}}, {"11.05.2021": {"plan": 0, "fact": 0}}, {"12.05.2021": {"plan": 0, "fact": 0}}, {"13.05.2021": {"plan": 0, "fact": 0}}, {"14.05.2021": {"plan": 0, "fact": 0}}, {"15.05.2021": {"plan": 0, "fact": 0}}, {"16.05.2021": {"plan": 0, "fact": 0}}, {"17.05.2021": {"plan": 0, "fact": 0}}, {"18.05.2021": {"plan": 0, "fact": 0}}, {"19.05.2021": {"plan": 0, "fact": 0}}, {"20.05.2021": {"plan": 0, "fact": 0}}, {"21.05.2021": {"plan": 0, "fact": 0}}, {"22.05.2021": {"plan": 0, "fact": 0}}, {"23.05.2021": {"plan": 0, "fact": 0}}, {"24.05.2021": {"plan": 0, "fact": 0}}, {"25.05.2021": {"plan": 0, "fact": 0}}, {"26.05.2021": {"plan": 0, "fact": 0}}, {"27.05.2021": {"plan": 0, "fact": 0}}, {"28.05.2021": {"plan": 0, "fact": 0}}, {"29.05.2021": {"plan": 0, "fact": 0}}, {"30.05.2021": {"plan": 0, "fact": 0}}, {"31.05.2021": {"plan": 0, "fact": 0}}], "comments": null}, {"resource_id": null, "resource_name": "Отделочник", "type": "human", "progress": [{"01.05.2021": {"plan": 0, "fact": 0}}, {"02.05.2021": {"plan": 0, "fact": 0}}, {"03.05.2021": {"plan": 0, "fact": 0}}, {"04.05.2021": {"plan": 0, "fact": 0}}, {"05.05.2021": {"plan": 0, "fact": 0}}, {"06.05.2021": {"plan": 0, "fact": 0}}, {"07.05.2021": {"plan": 0, "fact": 0}}, {"08.05.2021": {"plan": 0, "fact": 0}}, {"09.05.2021": {"plan": 0, "fact": 0}}, {"10.05.2021": {"plan": 0, "fact": 0}}, {"11.05.2021": {"plan": 0, "fact": 0}}, {"12.05.2021": {"plan": 0, "fact": 0}}, {"13.05.2021": {"plan": 0, "fact": 0}}, {"14.05.2021": {"plan": 0, "fact": 0}}, {"15.05.2021": {"plan": 0, "fact": 0}}, {"16.05.2021": {"plan": 0, "fact": 0}}, {"17.05.2021": {"plan": 0, "fact": 0}}, {"18.05.2021": {"plan": 0, "fact": 0}}, {"19.05.2021": {"plan": 0, "fact": 0}}, {"20.05.2021": {"plan": 0, "fact": 0}}, {"21.05.2021": {"plan": 0, "fact": 0}}, {"22.05.2021": {"plan": 0, "fact": 0}}, {"23.05.2021": {"plan": 0, "fact": 0}}, {"24.05.2021": {"plan": 0, "fact": 0}}, {"25.05.2021": {"plan": 0, "fact": 0}}, {"26.05.2021": {"plan": 0, "fact": 0}}, {"27.05.2021": {"plan": 0, "fact": 0}}, {"28.05.2021": {"plan": 0, "fact": 0}}, {"29.05.2021": {"plan": 0, "fact": 0}}, {"30.05.2021": {"plan": 0, "fact": 0}}, {"31.05.2021": {"plan": 0, "fact": 0}}], "comments": null}, {"resource_id": null, "resource_name": "Плотник, бетонщик, арматурщик", "type": "human", "progress": [{"01.05.2021": {"plan": 0, "fact": 0}}, {"02.05.2021": {"plan": 0, "fact": 0}}, {"03.05.2021": {"plan": 0, "fact": 0}}, {"04.05.2021": {"plan": 0, "fact": 0}}, {"05.05.2021": {"plan": 0, "fact": 0}}, {"06.05.2021": {"plan": 0, "fact": 0}}, {"07.05.2021": {"plan": 0, "fact": 0}}, {"08.05.2021": {"plan": 0, "fact": 0}}, {"09.05.2021": {"plan": 0, "fact": 0}}, {"10.05.2021": {"plan": 0, "fact": 0}}, {"11.05.2021": {"plan": 0, "fact": 0}}, {"12.05.2021": {"plan": 0, "fact": 0}}, {"13.05.2021": {"plan": 0, "fact": 0}}, {"14.05.2021": {"plan": 0, "fact": 0}}, {"15.05.2021": {"plan": 0, "fact": 0}}, {"16.05.2021": {"plan": 0, "fact": 0}}, {"17.05.2021": {"plan": 0, "fact": 0}}, {"18.05.2021": {"plan": 0, "fact": 0}}, {"19.05.2021": {"plan": 0, "fact": 0}}, {"20.05.2021": {"plan": 0, "fact": 0}}, {"21.05.2021": {"plan": 0, "fact": 0}}, {"22.05.2021": {"plan": 0, "fact": 0}}, {"23.05.2021": {"plan": 0, "fact": 0}}, {"24.05.2021": {"plan": 0, "fact": 0}}, {"25.05.2021": {"plan": 0, "fact": 0}}, {"26.05.2021": {"plan": 0, "fact": 0}}, {"27.05.2021": {"plan": 0, "fact": 0}}, {"28.05.2021": {"plan": 0, "fact": 0}}, {"29.05.2021": {"plan": 0, "fact": 0}}, {"30.05.2021": {"plan": 0, "fact": 0}}, {"31.05.2021": {"plan": 0, "fact": 0}}], "comments": null}, {"resource_id": null, "resource_name": "Разнорабочий", "type": "human", "progress": [{"01.05.2021": {"plan": 0, "fact": 0}}, {"02.05.2021": {"plan": 0, "fact": 0}}, {"03.05.2021": {"plan": 0, "fact": 0}}, {"04.05.2021": {"plan": 0, "fact": 0}}, {"05.05.2021": {"plan": 0, "fact": 0}}, {"06.05.2021": {"plan": 0, "fact": 0}}, {"07.05.2021": {"plan": 0, "fact": 0}}, {"08.05.2021": {"plan": 0, "fact": 0}}, {"09.05.2021": {"plan": 0, "fact": 0}}, {"10.05.2021": {"plan": 0, "fact": 0}}, {"11.05.2021": {"plan": 0, "fact": 0}}, {"12.05.2021": {"plan": 0, "fact": 0}}, {"13.05.2021": {"plan": 0, "fact": 0}}, {"14.05.2021": {"plan": 0, "fact": 0}}, {"15.05.2021": {"plan": 0, "fact": 0}}, {"16.05.2021": {"plan": 0, "fact": 0}}, {"17.05.2021": {"plan": 0, "fact": 0}}, {"18.05.2021": {"plan": 0, "fact": 0}}, {"19.05.2021": {"plan": 0, "fact": 0}}, {"20.05.2021": {"plan": 0, "fact": 0}}, {"21.05.2021": {"plan": 0, "fact": 0}}, {"22.05.2021": {"plan": 0, "fact": 0}}, {"23.05.2021": {"plan": 0, "fact": 0}}, {"24.05.2021": {"plan": 0, "fact": 0}}, {"25.05.2021": {"plan": 0, "fact": 0}}, {"26.05.2021": {"plan": 0, "fact": 0}}, {"27.05.2021": {"plan": 0, "fact": 0}}, {"28.05.2021": {"plan": 0, "fact": 0}}, {"29.05.2021": {"plan": 0, "fact": 0}}, {"30.05.2021": {"plan": 0, "fact": 0}}, {"31.05.2021": {"plan": 0, "fact": 0}}], "comments": null}, {"resource_id": null, "resource_name": "Сантехник", "type": "human", "progress": [{"01.05.2021": {"plan": 0, "fact": 0}}, {"02.05.2021": {"plan": 0, "fact": 0}}, {"03.05.2021": {"plan": 0, "fact": 0}}, {"04.05.2021": {"plan": 0, "fact": 0}}, {"05.05.2021": {"plan": 0, "fact": 0}}, {"06.05.2021": {"plan": 0, "fact": 0}}, {"07.05.2021": {"plan": 0, "fact": 0}}, {"08.05.2021": {"plan": 0, "fact": 0}}, {"09.05.2021": {"plan": 0, "fact": 0}}, {"10.05.2021": {"plan": 0, "fact": 0}}, {"11.05.2021": {"plan": 0, "fact": 0}}, {"12.05.2021": {"plan": 0, "fact": 0}}, {"13.05.2021": {"plan": 0, "fact": 0}}, {"14.05.2021": {"plan": 0, "fact": 0}}, {"15.05.2021": {"plan": 0, "fact": 0}}, {"16.05.2021": {"plan": 0, "fact": 0}}, {"17.05.2021": {"plan": 0, "fact": 0}}, {"18.05.2021": {"plan": 0, "fact": 0}}, {"19.05.2021": {"plan": 0, "fact": 0}}, {"20.05.2021": {"plan": 0, "fact": 0}}, {"21.05.2021": {"plan": 0, "fact": 0}}, {"22.05.2021": {"plan": 0, "fact": 0}}, {"23.05.2021": {"plan": 0, "fact": 0}}, {"24.05.2021": {"plan": 0, "fact": 0}}, {"25.05.2021": {"plan": 0, "fact": 0}}, {"26.05.2021": {"plan": 0, "fact": 0}}, {"27.05.2021": {"plan": 0, "fact": 0}}, {"28.05.2021": {"plan": 0, "fact": 0}}, {"29.05.2021": {"plan": 0, "fact": 0}}, {"30.05.2021": {"plan": 0, "fact": 0}}, {"31.05.2021": {"plan": 0, "fact": 0}}], "comments": null}, {"resource_id": null, "resource_name": "Сварщик МК (металлоконструкций)", "type": "human", "progress": [{"01.05.2021": {"plan": 0, "fact": 0}}, {"02.05.2021": {"plan": 0, "fact": 0}}, {"03.05.2021": {"plan": 0, "fact": 0}}, {"04.05.2021": {"plan": 0, "fact": 0}}, {"05.05.2021": {"plan": 0, "fact": 0}}, {"06.05.2021": {"plan": 0, "fact": 0}}, {"07.05.2021": {"plan": 0, "fact": 0}}, {"08.05.2021": {"plan": 0, "fact": 0}}, {"09.05.2021": {"plan": 0, "fact": 0}}, {"10.05.2021": {"plan": 0, "fact": 0}}, {"11.05.2021": {"plan": 0, "fact": 0}}, {"12.05.2021": {"plan": 0, "fact": 0}}, {"13.05.2021": {"plan": 0, "fact": 0}}, {"14.05.2021": {"plan": 0, "fact": 0}}, {"15.05.2021": {"plan": 0, "fact": 0}}, {"16.05.2021": {"plan": 0, "fact": 0}}, {"17.05.2021": {"plan": 0, "fact": 0}}, {"18.05.2021": {"plan": 0, "fact": 0}}, {"19.05.2021": {"plan": 0, "fact": 0}}, {"20.05.2021": {"plan": 0, "fact": 0}}, {"21.05.2021": {"plan": 0, "fact": 0}}, {"22.05.2021": {"plan": 0, "fact": 0}}, {"23.05.2021": {"plan": 0, "fact": 0}}, {"24.05.2021": {"plan": 0, "fact": 0}}, {"25.05.2021": {"plan": 0, "fact": 0}}, {"26.05.2021": {"plan": 0, "fact": 0}}, {"27.05.2021": {"plan": 0, "fact": 0}}, {"28.05.2021": {"plan": 0, "fact": 0}}, {"29.05.2021": {"plan": 0, "fact": 0}}, {"30.05.2021": {"plan": 0, "fact": 0}}, {"31.05.2021": {"plan": 0, "fact": 0}}], "comments": null}, {"resource_id": null, "resource_name": "Сварщик ТТ (технологических трубопроводов)", "type": "human", "progress": [{"01.05.2021": {"plan": 1, "fact": 0}}, {"02.05.2021": {"plan": 1, "fact": 0}}, {"03.05.2021": {"plan": 1, "fact": 0}}, {"04.05.2021": {"plan": 1, "fact": 0}}, {"05.05.2021": {"plan": 1, "fact": 0}}, {"06.05.2021": {"plan": 1, "fact": 1}}, {"07.05.2021": {"plan": 1, "fact": 0}}, {"08.05.2021": {"plan": 1, "fact": 0}}, {"09.05.2021": {"plan": 1, "fact": 0}}, {"10.05.2021": {"plan": 1, "fact": 0}}, {"11.05.2021": {"plan": 1, "fact": 0}}, {"12.05.2021": {"plan": 1, "fact": 0}}, {"13.05.2021": {"plan": 1, "fact": 0}}, {"14.05.2021": {"plan": 1, "fact": 0}}, {"15.05.2021": {"plan": 1, "fact": 0}}, {"16.05.2021": {"plan": 1, "fact": 0}}, {"17.05.2021": {"plan": 1, "fact": 0}}, {"18.05.2021": {"plan": 1, "fact": 0}}, {"19.05.2021": {"plan": 1, "fact": 0}}, {"20.05.2021": {"plan": 1, "fact": 0}}, {"21.05.2021": {"plan": 1, "fact": 0}}, {"22.05.2021": {"plan": 1, "fact": 0}}, {"23.05.2021": {"plan": 1, "fact": 0}}, {"24.05.2021": {"plan": 1, "fact": 0}}, {"25.05.2021": {"plan": 1, "fact": 0}}, {"26.05.2021": {"plan": 1, "fact": 0}}, {"27.05.2021": {"plan": 1, "fact": 0}}, {"28.05.2021": {"plan": 1, "fact": 0}}, {"29.05.2021": {"plan": 1, "fact": 0}}, {"30.05.2021": {"plan": 1, "fact": 0}}, {"31.05.2021": {"plan": 1, "fact": 0}}], "comments": null}, {"resource_id": null, "resource_name": "Слесарь", "type": "human", "progress": [{"01.05.2021": {"plan": 0, "fact": 0}}, {"02.05.2021": {"plan": 0, "fact": 0}}, {"03.05.2021": {"plan": 0, "fact": 0}}, {"04.05.2021": {"plan": 0, "fact": 0}}, {"05.05.2021": {"plan": 0, "fact": 0}}, {"06.05.2021": {"plan": 0, "fact": 0}}, {"07.05.2021": {"plan": 0, "fact": 0}}, {"08.05.2021": {"plan": 0, "fact": 0}}, {"09.05.2021": {"plan": 0, "fact": 0}}, {"10.05.2021": {"plan": 0, "fact": 0}}, {"11.05.2021": {"plan": 0, "fact": 0}}, {"12.05.2021": {"plan": 0, "fact": 0}}, {"13.05.2021": {"plan": 0, "fact": 0}}, {"14.05.2021": {"plan": 0, "fact": 0}}, {"15.05.2021": {"plan": 0, "fact": 0}}, {"16.05.2021": {"plan": 0, "fact": 0}}, {"17.05.2021": {"plan": 0, "fact": 0}}, {"18.05.2021": {"plan": 0, "fact": 0}}, {"19.05.2021": {"plan": 0, "fact": 0}}, {"20.05.2021": {"plan": 0, "fact": 0}}, {"21.05.2021": {"plan": 0, "fact": 0}}, {"22.05.2021": {"plan": 0, "fact": 0}}, {"23.05.2021": {"plan": 0, "fact": 0}}, {"24.05.2021": {"plan": 0, "fact": 0}}, {"25.05.2021": {"plan": 0, "fact": 0}}, {"26.05.2021": {"plan": 0, "fact": 0}}, {"27.05.2021": {"plan": 0, "fact": 0}}, {"28.05.2021": {"plan": 0, "fact": 0}}, {"29.05.2021": {"plan": 0, "fact": 0}}, {"30.05.2021": {"plan": 0, "fact": 0}}, {"31.05.2021": {"plan": 0, "fact": 0}}], "comments": null}, {"resource_id": null, "resource_name": "Слесарь КИПиА", "type": "human", "progress": [{"01.05.2021": {"plan": 0, "fact": 2}}, {"02.05.2021": {"plan": 0, "fact": 2}}, {"03.05.2021": {"plan": 0, "fact": 2}}, {"04.05.2021": {"plan": 0, "fact": 2}}, {"05.05.2021": {"plan": 0, "fact": 0}}, {"06.05.2021": {"plan": 0, "fact": 0}}, {"07.05.2021": {"plan": 0, "fact": 0}}, {"08.05.2021": {"plan": 0, "fact": 0}}, {"09.05.2021": {"plan": 0, "fact": 0}}, {"10.05.2021": {"plan": 0, "fact": 0}}, {"11.05.2021": {"plan": 0, "fact": 0}}, {"12.05.2021": {"plan": 0, "fact": 0}}, {"13.05.2021": {"plan": 0, "fact": 0}}, {"14.05.2021": {"plan": 0, "fact": 0}}, {"15.05.2021": {"plan": 0, "fact": 0}}, {"16.05.2021": {"plan": 0, "fact": 0}}, {"17.05.2021": {"plan": 0, "fact": 0}}, {"18.05.2021": {"plan": 0, "fact": 0}}, {"19.05.2021": {"plan": 0, "fact": 0}}, {"20.05.2021": {"plan": 0, "fact": 0}}, {"21.05.2021": {"plan": 0, "fact": 0}}, {"22.05.2021": {"plan": 0, "fact": 0}}, {"23.05.2021": {"plan": 0, "fact": 0}}, {"24.05.2021": {"plan": 0, "fact": 0}}, {"25.05.2021": {"plan": 0, "fact": 0}}, {"26.05.2021": {"plan": 0, "fact": 0}}, {"27.05.2021": {"plan": 0, "fact": 0}}, {"28.05.2021": {"plan": 0, "fact": 0}}, {"29.05.2021": {"plan": 0, "fact": 0}}, {"30.05.2021": {"plan": 0, "fact": 0}}, {"31.05.2021": {"plan": 0, "fact": 0}}], "comments": null}, {"resource_id": null, "resource_name": "Слесарь монтажник", "type": "human", "progress": [{"01.05.2021": {"plan": 0, "fact": 0}}, {"02.05.2021": {"plan": 0, "fact": 0}}, {"03.05.2021": {"plan": 0, "fact": 0}}, {"04.05.2021": {"plan": 0, "fact": 0}}, {"05.05.2021": {"plan": 0, "fact": 0}}, {"06.05.2021": {"plan": 0, "fact": 0}}, {"07.05.2021": {"plan": 0, "fact": 0}}, {"08.05.2021": {"plan": 0, "fact": 0}}, {"09.05.2021": {"plan": 0, "fact": 0}}, {"10.05.2021": {"plan": 0, "fact": 0}}, {"11.05.2021": {"plan": 0, "fact": 0}}, {"12.05.2021": {"plan": 0, "fact": 0}}, {"13.05.2021": {"plan": 0, "fact": 0}}, {"14.05.2021": {"plan": 0, "fact": 0}}, {"15.05.2021": {"plan": 0, "fact": 0}}, {"16.05.2021": {"plan": 0, "fact": 0}}, {"17.05.2021": {"plan": 0, "fact": 0}}, {"18.05.2021": {"plan": 0, "fact": 0}}, {"19.05.2021": {"plan": 0, "fact": 0}}, {"20.05.2021": {"plan": 0, "fact": 0}}, {"21.05.2021": {"plan": 0, "fact": 0}}, {"22.05.2021": {"plan": 0, "fact": 0}}, {"23.05.2021": {"plan": 0, "fact": 0}}, {"24.05.2021": {"plan": 0, "fact": 0}}, {"25.05.2021": {"plan": 0, "fact": 0}}, {"26.05.2021": {"plan": 0, "fact": 0}}, {"27.05.2021": {"plan": 0, "fact": 0}}, {"28.05.2021": {"plan": 0, "fact": 0}}, {"29.05.2021": {"plan": 0, "fact": 0}}, {"30.05.2021": {"plan": 0, "fact": 0}}, {"31.05.2021": {"plan": 0, "fact": 0}}], "comments": null}, {"resource_id": null, "resource_name": "Стропальщик", "type": "human", "progress": [{"01.05.2021": {"plan": 0, "fact": 0}}, {"02.05.2021": {"plan": 0, "fact": 0}}, {"03.05.2021": {"plan": 0, "fact": 0}}, {"04.05.2021": {"plan": 0, "fact": 0}}, {"05.05.2021": {"plan": 0, "fact": 0}}, {"06.05.2021": {"plan": 0, "fact": 0}}, {"07.05.2021": {"plan": 0, "fact": 0}}, {"08.05.2021": {"plan": 0, "fact": 0}}, {"09.05.2021": {"plan": 0, "fact": 0}}, {"10.05.2021": {"plan": 0, "fact": 0}}, {"11.05.2021": {"plan": 0, "fact": 0}}, {"12.05.2021": {"plan": 0, "fact": 0}}, {"13.05.2021": {"plan": 0, "fact": 0}}, {"14.05.2021": {"plan": 0, "fact": 0}}, {"15.05.2021": {"plan": 0, "fact": 0}}, {"16.05.2021": {"plan": 0, "fact": 0}}, {"17.05.2021": {"plan": 0, "fact": 0}}, {"18.05.2021": {"plan": 0, "fact": 0}}, {"19.05.2021": {"plan": 0, "fact": 0}}, {"20.05.2021": {"plan": 0, "fact": 0}}, {"21.05.2021": {"plan": 0, "fact": 0}}, {"22.05.2021": {"plan": 0, "fact": 0}}, {"23.05.2021": {"plan": 0, "fact": 0}}, {"24.05.2021": {"plan": 0, "fact": 0}}, {"25.05.2021": {"plan": 0, "fact": 0}}, {"26.05.2021": {"plan": 0, "fact": 0}}, {"27.05.2021": {"plan": 0, "fact": 0}}, {"28.05.2021": {"plan": 0, "fact": 0}}, {"29.05.2021": {"plan": 0, "fact": 0}}, {"30.05.2021": {"plan": 0, "fact": 0}}, {"31.05.2021": {"plan": 0, "fact": 0}}], "comments": null}, {"resource_id": null, "resource_name": "Электромонтажник", "type": "human", "progress": [{"01.05.2021": {"plan": 7, "fact": 6}}, {"02.05.2021": {"plan": 7, "fact": 6}}, {"03.05.2021": {"plan": 7, "fact": 6}}, {"04.05.2021": {"plan": 7, "fact": 5}}, {"05.05.2021": {"plan": 7, "fact": 5}}, {"06.05.2021": {"plan": 7, "fact": 6}}, {"07.05.2021": {"plan": 7, "fact": 0}}, {"08.05.2021": {"plan": 7, "fact": 1}}, {"09.05.2021": {"plan": 7, "fact": 0}}, {"10.05.2021": {"plan": 7, "fact": 0}}, {"11.05.2021": {"plan": 7, "fact": 0}}, {"12.05.2021": {"plan": 7, "fact": 0}}, {"13.05.2021": {"plan": 7, "fact": 0}}, {"14.05.2021": {"plan": 7, "fact": 0}}, {"15.05.2021": {"plan": 7, "fact": 0}}, {"16.05.2021": {"plan": 7, "fact": 0}}, {"17.05.2021": {"plan": 7, "fact": 0}}, {"18.05.2021": {"plan": 7, "fact": 0}}, {"19.05.2021": {"plan": 7, "fact": 0}}, {"20.05.2021": {"plan": 7, "fact": 0}}, {"21.05.2021": {"plan": 7, "fact": 5}}, {"22.05.2021": {"plan": 7, "fact": 5}}, {"23.05.2021": {"plan": 7, "fact": 4}}, {"24.05.2021": {"plan": 7, "fact": 4}}, {"25.05.2021": {"plan": 7, "fact": 5}}, {"26.05.2021": {"plan": 7, "fact": 4}}, {"27.05.2021": {"plan": 7, "fact": 4}}, {"28.05.2021": {"plan": 7, "fact": 4}}, {"29.05.2021": {"plan": 7, "fact": 4}}, {"30.05.2021": {"plan": 7, "fact": 4}}, {"31.05.2021": {"plan": 7, "fact": 4}}], "comments": null}, {"resource_id": null, "resource_name": "Прочие специальности", "type": "human", "progress": [{"01.05.2021": {"plan": 0, "fact": 0}}, {"02.05.2021": {"plan": 0, "fact": 0}}, {"03.05.2021": {"plan": 0, "fact": 0}}, {"04.05.2021": {"plan": 0, "fact": 0}}, {"05.05.2021": {"plan": 0, "fact": 0}}, {"06.05.2021": {"plan": 0, "fact": 0}}, {"07.05.2021": {"plan": 0, "fact": 0}}, {"08.05.2021": {"plan": 0, "fact": 0}}, {"09.05.2021": {"plan": 0, "fact": 0}}, {"10.05.2021": {"plan": 0, "fact": 0}}, {"11.05.2021": {"plan": 0, "fact": 0}}, {"12.05.2021": {"plan": 0, "fact": 0}}, {"13.05.2021": {"plan": 0, "fact": 0}}, {"14.05.2021": {"plan": 0, "fact": 0}}, {"15.05.2021": {"plan": 0, "fact": 0}}, {"16.05.2021": {"plan": 0, "fact": 0}}, {"17.05.2021": {"plan": 0, "fact": 0}}, {"18.05.2021": {"plan": 0, "fact": 0}}, {"19.05.2021": {"plan": 0, "fact": 0}}, {"20.05.2021": {"plan": 0, "fact": 0}}, {"21.05.2021": {"plan": 0, "fact": 0}}, {"22.05.2021": {"plan": 0, "fact": 0}}, {"23.05.2021": {"plan": 0, "fact": 0}}, {"24.05.2021": {"plan": 0, "fact": 0}}, {"25.05.2021": {"plan": 0, "fact": 0}}, {"26.05.2021": {"plan": 0, "fact": 0}}, {"27.05.2021": {"plan": 0, "fact": 0}}, {"28.05.2021": {"plan": 0, "fact": 0}}, {"29.05.2021": {"plan": 0, "fact": 0}}, {"30.05.2021": {"plan": 0, "fact": 0}}, {"31.05.2021": {"plan": 0, "fact": 0}}], "comments": null}, {"resource_id": null, "resource_name": "АДД (дизельный сварочный агрегат)", "type": "equipment", "progress": [{"01.05.2021": {"plan": 0, "fact": 0}}, {"02.05.2021": {"plan": 0, "fact": 0}}, {"03.05.2021": {"plan": 0, "fact": 0}}, {"04.05.2021": {"plan": 0, "fact": 0}}, {"05.05.2021": {"plan": 0, "fact": 0}}, {"06.05.2021": {"plan": 0, "fact": 0}}, {"07.05.2021": {"plan": 0, "fact": 0}}, {"08.05.2021": {"plan": 0, "fact": 0}}, {"09.05.2021": {"plan": 0, "fact": 0}}, {"10.05.2021": {"plan": 0, "fact": 0}}, {"11.05.2021": {"plan": 0, "fact": 0}}, {"12.05.2021": {"plan": 0, "fact": 0}}, {"13.05.2021": {"plan": 0, "fact": 0}}, {"14.05.2021": {"plan": 0, "fact": 0}}, {"15.05.2021": {"plan": 0, "fact": 0}}, {"16.05.2021": {"plan": 0, "fact": 0}}, {"17.05.2021": {"plan": 0, "fact": 0}}, {"18.05.2021": {"plan": 0, "fact": 0}}, {"19.05.2021": {"plan": 0, "fact": 0}}, {"20.05.2021": {"plan": 0, "fact": 0}}, {"21.05.2021": {"plan": 0, "fact": 0}}, {"22.05.2021": {"plan": 0, "fact": 0}}, {"23.05.2021": {"plan": 0, "fact": 0}}, {"24.05.2021": {"plan": 0, "fact": 0}}, {"25.05.2021": {"plan": 0, "fact": 0}}, {"26.05.2021": {"plan": 0, "fact": 0}}, {"27.05.2021": {"plan": 0, "fact": 0}}, {"28.05.2021": {"plan": 0, "fact": 0}}, {"29.05.2021": {"plan": 0, "fact": 0}}, {"30.05.2021": {"plan": 0, "fact": 0}}, {"31.05.2021": {"plan": 0, "fact": 0}}], "comments": null}, {"resource_id": null, "resource_name": "АПС (агрегат передвижной сварочный)", "type": "equipment", "progress": [{"01.05.2021": {"plan": 0, "fact": 0}}, {"02.05.2021": {"plan": 0, "fact": 0}}, {"03.05.2021": {"plan": 0, "fact": 0}}, {"04.05.2021": {"plan": 0, "fact": 0}}, {"05.05.2021": {"plan": 0, "fact": 0}}, {"06.05.2021": {"plan": 0, "fact": 0}}, {"07.05.2021": {"plan": 0, "fact": 0}}, {"08.05.2021": {"plan": 0, "fact": 0}}, {"09.05.2021": {"plan": 0, "fact": 0}}, {"10.05.2021": {"plan": 0, "fact": 0}}, {"11.05.2021": {"plan": 0, "fact": 0}}, {"12.05.2021": {"plan": 0, "fact": 0}}, {"13.05.2021": {"plan": 0, "fact": 0}}, {"14.05.2021": {"plan": 0, "fact": 0}}, {"15.05.2021": {"plan": 0, "fact": 0}}, {"16.05.2021": {"plan": 0, "fact": 0}}, {"17.05.2021": {"plan": 0, "fact": 0}}, {"18.05.2021": {"plan": 0, "fact": 0}}, {"19.05.2021": {"plan": 0, "fact": 0}}, {"20.05.2021": {"plan": 0, "fact": 0}}, {"21.05.2021": {"plan": 0, "fact": 0}}, {"22.05.2021": {"plan": 0, "fact": 0}}, {"23.05.2021": {"plan": 0, "fact": 0}}, {"24.05.2021": {"plan": 0, "fact": 0}}, {"25.05.2021": {"plan": 0, "fact": 0}}, {"26.05.2021": {"plan": 0, "fact": 0}}, {"27.05.2021": {"plan": 0, "fact": 0}}, {"28.05.2021": {"plan": 0, "fact": 0}}, {"29.05.2021": {"plan": 0, "fact": 0}}, {"30.05.2021": {"plan": 0, "fact": 0}}, {"31.05.2021": {"plan": 0, "fact": 0}}], "comments": null}, {"resource_id": null, "resource_name": "АРОК (агрегат ремонта и обслуживания)", "type": "equipment", "progress": [{"01.05.2021": {"plan": 0, "fact": 0}}, {"02.05.2021": {"plan": 0, "fact": 0}}, {"03.05.2021": {"plan": 0, "fact": 0}}, {"04.05.2021": {"plan": 0, "fact": 0}}, {"05.05.2021": {"plan": 0, "fact": 0}}, {"06.05.2021": {"plan": 0, "fact": 0}}, {"07.05.2021": {"plan": 0, "fact": 0}}, {"08.05.2021": {"plan": 0, "fact": 0}}, {"09.05.2021": {"plan": 0, "fact": 0}}, {"10.05.2021": {"plan": 0, "fact": 0}}, {"11.05.2021": {"plan": 0, "fact": 0}}, {"12.05.2021": {"plan": 0, "fact": 0}}, {"13.05.2021": {"plan": 0, "fact": 0}}, {"14.05.2021": {"plan": 0, "fact": 0}}, {"15.05.2021": {"plan": 0, "fact": 0}}, {"16.05.2021": {"plan": 0, "fact": 0}}, {"17.05.2021": {"plan": 0, "fact": 0}}, {"18.05.2021": {"plan": 0, "fact": 0}}, {"19.05.2021": {"plan": 0, "fact": 0}}, {"20.05.2021": {"plan": 0, "fact": 0}}, {"21.05.2021": {"plan": 0, "fact": 0}}, {"22.05.2021": {"plan": 0, "fact": 0}}, {"23.05.2021": {"plan": 0, "fact": 0}}, {"24.05.2021": {"plan": 0, "fact": 0}}, {"25.05.2021": {"plan": 0, "fact": 0}}, {"26.05.2021": {"plan": 0, "fact": 0}}, {"27.05.2021": {"plan": 0, "fact": 0}}, {"28.05.2021": {"plan": 0, "fact": 0}}, {"29.05.2021": {"plan": 0, "fact": 0}}, {"30.05.2021": {"plan": 0, "fact": 0}}, {"31.05.2021": {"plan": 0, "fact": 0}}], "comments": null}, {"resource_id": null, "resource_name": "Бензовоз", "type": "equipment", "progress": [{"01.05.2021": {"plan": 0, "fact": 0}}, {"02.05.2021": {"plan": 0, "fact": 0}}, {"03.05.2021": {"plan": 0, "fact": 0}}, {"04.05.2021": {"plan": 0, "fact": 0}}, {"05.05.2021": {"plan": 0, "fact": 0}}, {"06.05.2021": {"plan": 0, "fact": 0}}, {"07.05.2021": {"plan": 0, "fact": 0}}, {"08.05.2021": {"plan": 0, "fact": 0}}, {"09.05.2021": {"plan": 0, "fact": 0}}, {"10.05.2021": {"plan": 0, "fact": 0}}, {"11.05.2021": {"plan": 0, "fact": 0}}, {"12.05.2021": {"plan": 0, "fact": 0}}, {"13.05.2021": {"plan": 0, "fact": 0}}, {"14.05.2021": {"plan": 0, "fact": 0}}, {"15.05.2021": {"plan": 0, "fact": 0}}, {"16.05.2021": {"plan": 0, "fact": 0}}, {"17.05.2021": {"plan": 0, "fact": 0}}, {"18.05.2021": {"plan": 0, "fact": 0}}, {"19.05.2021": {"plan": 0, "fact": 0}}, {"20.05.2021": {"plan": 0, "fact": 0}}, {"21.05.2021": {"plan": 0, "fact": 0}}, {"22.05.2021": {"plan": 0, "fact": 0}}, {"23.05.2021": {"plan": 0, "fact": 0}}, {"24.05.2021": {"plan": 0, "fact": 0}}, {"25.05.2021": {"plan": 0, "fact": 0}}, {"26.05.2021": {"plan": 0, "fact": 0}}, {"27.05.2021": {"plan": 0, "fact": 0}}, {"28.05.2021": {"plan": 0, "fact": 0}}, {"29.05.2021": {"plan": 0, "fact": 0}}, {"30.05.2021": {"plan": 0, "fact": 0}}, {"31.05.2021": {"plan": 0, "fact": 0}}], "comments": null}, {"resource_id": null, "resource_name": "Бортовой автомобиль", "type": "equipment", "progress": [{"01.05.2021": {"plan": 0, "fact": 0}}, {"02.05.2021": {"plan": 0, "fact": 0}}, {"03.05.2021": {"plan": 0, "fact": 0}}, {"04.05.2021": {"plan": 0, "fact": 0}}, {"05.05.2021": {"plan": 0, "fact": 0}}, {"06.05.2021": {"plan": 0, "fact": 0}}, {"07.05.2021": {"plan": 0, "fact": 0}}, {"08.05.2021": {"plan": 0, "fact": 0}}, {"09.05.2021": {"plan": 0, "fact": 0}}, {"10.05.2021": {"plan": 0, "fact": 0}}, {"11.05.2021": {"plan": 0, "fact": 0}}, {"12.05.2021": {"plan": 0, "fact": 0}}, {"13.05.2021": {"plan": 0, "fact": 0}}, {"14.05.2021": {"plan": 0, "fact": 0}}, {"15.05.2021": {"plan": 0, "fact": 0}}, {"16.05.2021": {"plan": 0, "fact": 0}}, {"17.05.2021": {"plan": 0, "fact": 0}}, {"18.05.2021": {"plan": 0, "fact": 0}}, {"19.05.2021": {"plan": 0, "fact": 0}}, {"20.05.2021": {"plan": 0, "fact": 0}}, {"21.05.2021": {"plan": 0, "fact": 0}}, {"22.05.2021": {"plan": 0, "fact": 0}}, {"23.05.2021": {"plan": 0, "fact": 0}}, {"24.05.2021": {"plan": 0, "fact": 0}}, {"25.05.2021": {"plan": 0, "fact": 0}}, {"26.05.2021": {"plan": 0, "fact": 0}}, {"27.05.2021": {"plan": 0, "fact": 0}}, {"28.05.2021": {"plan": 0, "fact": 0}}, {"29.05.2021": {"plan": 0, "fact": 0}}, {"30.05.2021": {"plan": 0, "fact": 0}}, {"31.05.2021": {"plan": 0, "fact": 0}}], "comments": null}, {"resource_id": null, "resource_name": "Бульдозер", "type": "equipment", "progress": [{"01.05.2021": {"plan": 0, "fact": 0}}, {"02.05.2021": {"plan": 0, "fact": 0}}, {"03.05.2021": {"plan": 0, "fact": 0}}, {"04.05.2021": {"plan": 0, "fact": 0}}, {"05.05.2021": {"plan": 0, "fact": 0}}, {"06.05.2021": {"plan": 0, "fact": 0}}, {"07.05.2021": {"plan": 0, "fact": 0}}, {"08.05.2021": {"plan": 0, "fact": 0}}, {"09.05.2021": {"plan": 0, "fact": 0}}, {"10.05.2021": {"plan": 0, "fact": 0}}, {"11.05.2021": {"plan": 0, "fact": 0}}, {"12.05.2021": {"plan": 0, "fact": 0}}, {"13.05.2021": {"plan": 0, "fact": 0}}, {"14.05.2021": {"plan": 0, "fact": 0}}, {"15.05.2021": {"plan": 0, "fact": 0}}, {"16.05.2021": {"plan": 0, "fact": 0}}, {"17.05.2021": {"plan": 0, "fact": 0}}, {"18.05.2021": {"plan": 0, "fact": 0}}, {"19.05.2021": {"plan": 0, "fact": 0}}, {"20.05.2021": {"plan": 0, "fact": 0}}, {"21.05.2021": {"plan": 0, "fact": 0}}, {"22.05.2021": {"plan": 0, "fact": 0}}, {"23.05.2021": {"plan": 0, "fact": 0}}, {"24.05.2021": {"plan": 0, "fact": 0}}, {"25.05.2021": {"plan": 0, "fact": 0}}, {"26.05.2021": {"plan": 0, "fact": 0}}, {"27.05.2021": {"plan": 0, "fact": 0}}, {"28.05.2021": {"plan": 0, "fact": 0}}, {"29.05.2021": {"plan": 0, "fact": 0}}, {"30.05.2021": {"plan": 0, "fact": 0}}, {"31.05.2021": {"plan": 0, "fact": 0}}], "comments": null}, {"resource_id": null, "resource_name": "Бурильная машина", "type": "equipment", "progress": [{"01.05.2021": {"plan": 0, "fact": 0}}, {"02.05.2021": {"plan": 0, "fact": 0}}, {"03.05.2021": {"plan": 0, "fact": 0}}, {"04.05.2021": {"plan": 0, "fact": 0}}, {"05.05.2021": {"plan": 0, "fact": 0}}, {"06.05.2021": {"plan": 0, "fact": 0}}, {"07.05.2021": {"plan": 0, "fact": 0}}, {"08.05.2021": {"plan": 0, "fact": 0}}, {"09.05.2021": {"plan": 0, "fact": 0}}, {"10.05.2021": {"plan": 0, "fact": 0}}, {"11.05.2021": {"plan": 0, "fact": 0}}, {"12.05.2021": {"plan": 0, "fact": 0}}, {"13.05.2021": {"plan": 0, "fact": 0}}, {"14.05.2021": {"plan": 0, "fact": 0}}, {"15.05.2021": {"plan": 0, "fact": 0}}, {"16.05.2021": {"plan": 0, "fact": 0}}, {"17.05.2021": {"plan": 0, "fact": 0}}, {"18.05.2021": {"plan": 0, "fact": 0}}, {"19.05.2021": {"plan": 0, "fact": 0}}, {"20.05.2021": {"plan": 0, "fact": 0}}, {"21.05.2021": {"plan": 0, "fact": 0}}, {"22.05.2021": {"plan": 0, "fact": 0}}, {"23.05.2021": {"plan": 0, "fact": 0}}, {"24.05.2021": {"plan": 0, "fact": 0}}, {"25.05.2021": {"plan": 0, "fact": 0}}, {"26.05.2021": {"plan": 0, "fact": 0}}, {"27.05.2021": {"plan": 0, "fact": 0}}, {"28.05.2021": {"plan": 0, "fact": 0}}, {"29.05.2021": {"plan": 0, "fact": 0}}, {"30.05.2021": {"plan": 0, "fact": 0}}, {"31.05.2021": {"plan": 0, "fact": 0}}], "comments": null}, {"resource_id": null, "resource_name": "Вахтовый автобус", "type": "equipment", "progress": [{"01.05.2021": {"plan": 1, "fact": 1}}, {"02.05.2021": {"plan": 1, "fact": 1}}, {"03.05.2021": {"plan": 1, "fact": 1}}, {"04.05.2021": {"plan": 1, "fact": 1}}, {"05.05.2021": {"plan": 1, "fact": 1}}, {"06.05.2021": {"plan": 1, "fact": 1}}, {"07.05.2021": {"plan": 1, "fact": 0}}, {"08.05.2021": {"plan": 1, "fact": 1}}, {"09.05.2021": {"plan": 1, "fact": 0}}, {"10.05.2021": {"plan": 1, "fact": 0}}, {"11.05.2021": {"plan": 1, "fact": 0}}, {"12.05.2021": {"plan": 1, "fact": 0}}, {"13.05.2021": {"plan": 1, "fact": 0}}, {"14.05.2021": {"plan": 1, "fact": 0}}, {"15.05.2021": {"plan": 1, "fact": 0}}, {"16.05.2021": {"plan": 1, "fact": 0}}, {"17.05.2021": {"plan": 1, "fact": 0}}, {"18.05.2021": {"plan": 1, "fact": 0}}, {"19.05.2021": {"plan": 1, "fact": 0}}, {"20.05.2021": {"plan": 1, "fact": 0}}, {"21.05.2021": {"plan": 1, "fact": 1}}, {"22.05.2021": {"plan": 1, "fact": 1}}, {"23.05.2021": {"plan": 1, "fact": 1}}, {"24.05.2021": {"plan": 1, "fact": 1}}, {"25.05.2021": {"plan": 1, "fact": 1}}, {"26.05.2021": {"plan": 1, "fact": 1}}, {"27.05.2021": {"plan": 1, "fact": 1}}, {"28.05.2021": {"plan": 1, "fact": 1}}, {"29.05.2021": {"plan": 1, "fact": 1}}, {"30.05.2021": {"plan": 1, "fact": 1}}, {"31.05.2021": {"plan": 1, "fact": 0}}], "comments": null}, {"resource_id": null, "resource_name": "Вибропогружатель", "type": "equipment", "progress": [{"01.05.2021": {"plan": 0, "fact": 0}}, {"02.05.2021": {"plan": 0, "fact": 0}}, {"03.05.2021": {"plan": 0, "fact": 0}}, {"04.05.2021": {"plan": 0, "fact": 0}}, {"05.05.2021": {"plan": 0, "fact": 0}}, {"06.05.2021": {"plan": 0, "fact": 0}}, {"07.05.2021": {"plan": 0, "fact": 0}}, {"08.05.2021": {"plan": 0, "fact": 0}}, {"09.05.2021": {"plan": 0, "fact": 0}}, {"10.05.2021": {"plan": 0, "fact": 0}}, {"11.05.2021": {"plan": 0, "fact": 0}}, {"12.05.2021": {"plan": 0, "fact": 0}}, {"13.05.2021": {"plan": 0, "fact": 0}}, {"14.05.2021": {"plan": 0, "fact": 0}}, {"15.05.2021": {"plan": 0, "fact": 0}}, {"16.05.2021": {"plan": 0, "fact": 0}}, {"17.05.2021": {"plan": 0, "fact": 0}}, {"18.05.2021": {"plan": 0, "fact": 0}}, {"19.05.2021": {"plan": 0, "fact": 0}}, {"20.05.2021": {"plan": 0, "fact": 0}}, {"21.05.2021": {"plan": 0, "fact": 0}}, {"22.05.2021": {"plan": 0, "fact": 0}}, {"23.05.2021": {"plan": 0, "fact": 0}}, {"24.05.2021": {"plan": 0, "fact": 0}}, {"25.05.2021": {"plan": 0, "fact": 0}}, {"26.05.2021": {"plan": 0, "fact": 0}}, {"27.05.2021": {"plan": 0, "fact": 0}}, {"28.05.2021": {"plan": 0, "fact": 0}}, {"29.05.2021": {"plan": 0, "fact": 0}}, {"30.05.2021": {"plan": 0, "fact": 0}}, {"31.05.2021": {"plan": 0, "fact": 0}}], "comments": null}, {"resource_id": null, "resource_name": "Водовоз", "type": "equipment", "progress": [{"01.05.2021": {"plan": 0, "fact": 0}}, {"02.05.2021": {"plan": 0, "fact": 0}}, {"03.05.2021": {"plan": 0, "fact": 0}}, {"04.05.2021": {"plan": 0, "fact": 0}}, {"05.05.2021": {"plan": 0, "fact": 0}}, {"06.05.2021": {"plan": 0, "fact": 0}}, {"07.05.2021": {"plan": 0, "fact": 0}}, {"08.05.2021": {"plan": 0, "fact": 0}}, {"09.05.2021": {"plan": 0, "fact": 0}}, {"10.05.2021": {"plan": 0, "fact": 0}}, {"11.05.2021": {"plan": 0, "fact": 0}}, {"12.05.2021": {"plan": 0, "fact": 0}}, {"13.05.2021": {"plan": 0, "fact": 0}}, {"14.05.2021": {"plan": 0, "fact": 0}}, {"15.05.2021": {"plan": 0, "fact": 0}}, {"16.05.2021": {"plan": 0, "fact": 0}}, {"17.05.2021": {"plan": 0, "fact": 0}}, {"18.05.2021": {"plan": 0, "fact": 0}}, {"19.05.2021": {"plan": 0, "fact": 0}}, {"20.05.2021": {"plan": 0, "fact": 0}}, {"21.05.2021": {"plan": 0, "fact": 0}}, {"22.05.2021": {"plan": 0, "fact": 0}}, {"23.05.2021": {"plan": 0, "fact": 0}}, {"24.05.2021": {"plan": 0, "fact": 0}}, {"25.05.2021": {"plan": 0, "fact": 0}}, {"26.05.2021": {"plan": 0, "fact": 0}}, {"27.05.2021": {"plan": 0, "fact": 0}}, {"28.05.2021": {"plan": 0, "fact": 0}}, {"29.05.2021": {"plan": 0, "fact": 0}}, {"30.05.2021": {"plan": 0, "fact": 0}}, {"31.05.2021": {"plan": 0, "fact": 0}}], "comments": null}, {"resource_id": null, "resource_name": "Экскаватор", "type": "equipment", "progress": [{"01.05.2021": {"plan": 0, "fact": 0}}, {"02.05.2021": {"plan": 0, "fact": 0}}, {"03.05.2021": {"plan": 0, "fact": 0}}, {"04.05.2021": {"plan": 0, "fact": 0}}, {"05.05.2021": {"plan": 0, "fact": 0}}, {"06.05.2021": {"plan": 0, "fact": 0}}, {"07.05.2021": {"plan": 0, "fact": 0}}, {"08.05.2021": {"plan": 0, "fact": 0}}, {"09.05.2021": {"plan": 0, "fact": 0}}, {"10.05.2021": {"plan": 0, "fact": 0}}, {"11.05.2021": {"plan": 0, "fact": 0}}, {"12.05.2021": {"plan": 0, "fact": 0}}, {"13.05.2021": {"plan": 0, "fact": 0}}, {"14.05.2021": {"plan": 0, "fact": 0}}, {"15.05.2021": {"plan": 0, "fact": 0}}, {"16.05.2021": {"plan": 0, "fact": 0}}, {"17.05.2021": {"plan": 0, "fact": 0}}, {"18.05.2021": {"plan": 0, "fact": 0}}, {"19.05.2021": {"plan": 0, "fact": 0}}, {"20.05.2021": {"plan": 0, "fact": 0}}, {"21.05.2021": {"plan": 0, "fact": 0}}, {"22.05.2021": {"plan": 0, "fact": 0}}, {"23.05.2021": {"plan": 0, "fact": 0}}, {"24.05.2021": {"plan": 0, "fact": 0}}, {"25.05.2021": {"plan": 0, "fact": 0}}, {"26.05.2021": {"plan": 0, "fact": 0}}, {"27.05.2021": {"plan": 0, "fact": 0}}, {"28.05.2021": {"plan": 0, "fact": 0}}, {"29.05.2021": {"plan": 0, "fact": 0}}, {"30.05.2021": {"plan": 0, "fact": 0}}, {"31.05.2021": {"plan": 0, "fact": 0}}], "comments": null}, {"resource_id": null, "resource_name": "ДЭС (дизельная электростанция)", "type": "equipment", "progress": [{"01.05.2021": {"plan": 0, "fact": 0}}, {"02.05.2021": {"plan": 0, "fact": 0}}, {"03.05.2021": {"plan": 0, "fact": 0}}, {"04.05.2021": {"plan": 0, "fact": 0}}, {"05.05.2021": {"plan": 0, "fact": 0}}, {"06.05.2021": {"plan": 0, "fact": 0}}, {"07.05.2021": {"plan": 0, "fact": 0}}, {"08.05.2021": {"plan": 0, "fact": 0}}, {"09.05.2021": {"plan": 0, "fact": 0}}, {"10.05.2021": {"plan": 0, "fact": 0}}, {"11.05.2021": {"plan": 0, "fact": 0}}, {"12.05.2021": {"plan": 0, "fact": 0}}, {"13.05.2021": {"plan": 0, "fact": 0}}, {"14.05.2021": {"plan": 0, "fact": 0}}, {"15.05.2021": {"plan": 0, "fact": 0}}, {"16.05.2021": {"plan": 0, "fact": 0}}, {"17.05.2021": {"plan": 0, "fact": 0}}, {"18.05.2021": {"plan": 0, "fact": 0}}, {"19.05.2021": {"plan": 0, "fact": 0}}, {"20.05.2021": {"plan": 0, "fact": 0}}, {"21.05.2021": {"plan": 0, "fact": 0}}, {"22.05.2021": {"plan": 0, "fact": 0}}, {"23.05.2021": {"plan": 0, "fact": 0}}, {"24.05.2021": {"plan": 0, "fact": 0}}, {"25.05.2021": {"plan": 0, "fact": 0}}, {"26.05.2021": {"plan": 0, "fact": 0}}, {"27.05.2021": {"plan": 0, "fact": 0}}, {"28.05.2021": {"plan": 0, "fact": 0}}, {"29.05.2021": {"plan": 0, "fact": 0}}, {"30.05.2021": {"plan": 0, "fact": 0}}, {"31.05.2021": {"plan": 0, "fact": 0}}], "comments": null}, {"resource_id": null, "resource_name": "Каток", "type": "equipment", "progress": [{"01.05.2021": {"plan": 0, "fact": 0}}, {"02.05.2021": {"plan": 0, "fact": 0}}, {"03.05.2021": {"plan": 0, "fact": 0}}, {"04.05.2021": {"plan": 0, "fact": 0}}, {"05.05.2021": {"plan": 0, "fact": 0}}, {"06.05.2021": {"plan": 0, "fact": 0}}, {"07.05.2021": {"plan": 0, "fact": 0}}, {"08.05.2021": {"plan": 0, "fact": 0}}, {"09.05.2021": {"plan": 0, "fact": 0}}, {"10.05.2021": {"plan": 0, "fact": 0}}, {"11.05.2021": {"plan": 0, "fact": 0}}, {"12.05.2021": {"plan": 0, "fact": 0}}, {"13.05.2021": {"plan": 0, "fact": 0}}, {"14.05.2021": {"plan": 0, "fact": 0}}, {"15.05.2021": {"plan": 0, "fact": 0}}, {"16.05.2021": {"plan": 0, "fact": 0}}, {"17.05.2021": {"plan": 0, "fact": 0}}, {"18.05.2021": {"plan": 0, "fact": 0}}, {"19.05.2021": {"plan": 0, "fact": 0}}, {"20.05.2021": {"plan": 0, "fact": 0}}, {"21.05.2021": {"plan": 0, "fact": 0}}, {"22.05.2021": {"plan": 0, "fact": 0}}, {"23.05.2021": {"plan": 0, "fact": 0}}, {"24.05.2021": {"plan": 0, "fact": 0}}, {"25.05.2021": {"plan": 0, "fact": 0}}, {"26.05.2021": {"plan": 0, "fact": 0}}, {"27.05.2021": {"plan": 0, "fact": 0}}, {"28.05.2021": {"plan": 0, "fact": 0}}, {"29.05.2021": {"plan": 0, "fact": 0}}, {"30.05.2021": {"plan": 0, "fact": 0}}, {"31.05.2021": {"plan": 0, "fact": 0}}], "comments": null}, {"resource_id": null, "resource_name": "Автокран", "type": "equipment", "progress": [{"01.05.2021": {"plan": 0, "fact": 0}}, {"02.05.2021": {"plan": 0, "fact": 0}}, {"03.05.2021": {"plan": 0, "fact": 0}}, {"04.05.2021": {"plan": 0, "fact": 0}}, {"05.05.2021": {"plan": 0, "fact": 0}}, {"06.05.2021": {"plan": 0, "fact": 0}}, {"07.05.2021": {"plan": 0, "fact": 0}}, {"08.05.2021": {"plan": 0, "fact": 0}}, {"09.05.2021": {"plan": 0, "fact": 0}}, {"10.05.2021": {"plan": 0, "fact": 0}}, {"11.05.2021": {"plan": 0, "fact": 0}}, {"12.05.2021": {"plan": 0, "fact": 0}}, {"13.05.2021": {"plan": 0, "fact": 0}}, {"14.05.2021": {"plan": 0, "fact": 0}}, {"15.05.2021": {"plan": 0, "fact": 0}}, {"16.05.2021": {"plan": 0, "fact": 0}}, {"17.05.2021": {"plan": 0, "fact": 0}}, {"18.05.2021": {"plan": 0, "fact": 0}}, {"19.05.2021": {"plan": 0, "fact": 0}}, {"20.05.2021": {"plan": 0, "fact": 0}}, {"21.05.2021": {"plan": 0, "fact": 0}}, {"22.05.2021": {"plan": 0, "fact": 0}}, {"23.05.2021": {"plan": 0, "fact": 0}}, {"24.05.2021": {"plan": 0, "fact": 0}}, {"25.05.2021": {"plan": 0, "fact": 0}}, {"26.05.2021": {"plan": 0, "fact": 0}}, {"27.05.2021": {"plan": 0, "fact": 0}}, {"28.05.2021": {"plan": 0, "fact": 0}}, {"29.05.2021": {"plan": 0, "fact": 0}}, {"30.05.2021": {"plan": 0, "fact": 0}}, {"31.05.2021": {"plan": 0, "fact": 0}}], "comments": null}, {"resource_id": null, "resource_name": "Кран стреловой", "type": "equipment", "progress": [{"01.05.2021": {"plan": 0, "fact": 0}}, {"02.05.2021": {"plan": 0, "fact": 0}}, {"03.05.2021": {"plan": 0, "fact": 0}}, {"04.05.2021": {"plan": 0, "fact": 0}}, {"05.05.2021": {"plan": 0, "fact": 0}}, {"06.05.2021": {"plan": 0, "fact": 0}}, {"07.05.2021": {"plan": 0, "fact": 0}}, {"08.05.2021": {"plan": 0, "fact": 0}}, {"09.05.2021": {"plan": 0, "fact": 0}}, {"10.05.2021": {"plan": 0, "fact": 0}}, {"11.05.2021": {"plan": 0, "fact": 0}}, {"12.05.2021": {"plan": 0, "fact": 0}}, {"13.05.2021": {"plan": 0, "fact": 0}}, {"14.05.2021": {"plan": 0, "fact": 0}}, {"15.05.2021": {"plan": 0, "fact": 0}}, {"16.05.2021": {"plan": 0, "fact": 0}}, {"17.05.2021": {"plan": 0, "fact": 0}}, {"18.05.2021": {"plan": 0, "fact": 0}}, {"19.05.2021": {"plan": 0, "fact": 0}}, {"20.05.2021": {"plan": 0, "fact": 0}}, {"21.05.2021": {"plan": 0, "fact": 0}}, {"22.05.2021": {"plan": 0, "fact": 0}}, {"23.05.2021": {"plan": 0, "fact": 0}}, {"24.05.2021": {"plan": 0, "fact": 0}}, {"25.05.2021": {"plan": 0, "fact": 0}}, {"26.05.2021": {"plan": 0, "fact": 0}}, {"27.05.2021": {"plan": 0, "fact": 0}}, {"28.05.2021": {"plan": 0, "fact": 0}}, {"29.05.2021": {"plan": 0, "fact": 0}}, {"30.05.2021": {"plan": 0, "fact": 0}}, {"31.05.2021": {"plan": 0, "fact": 0}}], "comments": null}, {"resource_id": null, "resource_name": "Бетономешалка", "type": "equipment", "progress": [{"01.05.2021": {"plan": 0, "fact": 0}}, {"02.05.2021": {"plan": 0, "fact": 0}}, {"03.05.2021": {"plan": 0, "fact": 0}}, {"04.05.2021": {"plan": 0, "fact": 0}}, {"05.05.2021": {"plan": 0, "fact": 0}}, {"06.05.2021": {"plan": 0, "fact": 0}}, {"07.05.2021": {"plan": 0, "fact": 0}}, {"08.05.2021": {"plan": 0, "fact": 0}}, {"09.05.2021": {"plan": 0, "fact": 0}}, {"10.05.2021": {"plan": 0, "fact": 0}}, {"11.05.2021": {"plan": 0, "fact": 0}}, {"12.05.2021": {"plan": 0, "fact": 0}}, {"13.05.2021": {"plan": 0, "fact": 0}}, {"14.05.2021": {"plan": 0, "fact": 0}}, {"15.05.2021": {"plan": 0, "fact": 0}}, {"16.05.2021": {"plan": 0, "fact": 0}}, {"17.05.2021": {"plan": 0, "fact": 0}}, {"18.05.2021": {"plan": 0, "fact": 0}}, {"19.05.2021": {"plan": 0, "fact": 0}}, {"20.05.2021": {"plan": 0, "fact": 0}}, {"21.05.2021": {"plan": 0, "fact": 0}}, {"22.05.2021": {"plan": 0, "fact": 0}}, {"23.05.2021": {"plan": 0, "fact": 0}}, {"24.05.2021": {"plan": 0, "fact": 0}}, {"25.05.2021": {"plan": 0, "fact": 0}}, {"26.05.2021": {"plan": 0, "fact": 0}}, {"27.05.2021": {"plan": 0, "fact": 0}}, {"28.05.2021": {"plan": 0, "fact": 0}}, {"29.05.2021": {"plan": 0, "fact": 0}}, {"30.05.2021": {"plan": 0, "fact": 0}}, {"31.05.2021": {"plan": 0, "fact": 0}}], "comments": null}, {"resource_id": null, "resource_name": "Погрузчик", "type": "equipment", "progress": [{"01.05.2021": {"plan": 0, "fact": 0}}, {"02.05.2021": {"plan": 0, "fact": 0}}, {"03.05.2021": {"plan": 0, "fact": 0}}, {"04.05.2021": {"plan": 0, "fact": 0}}, {"05.05.2021": {"plan": 0, "fact": 0}}, {"06.05.2021": {"plan": 0, "fact": 0}}, {"07.05.2021": {"plan": 0, "fact": 0}}, {"08.05.2021": {"plan": 0, "fact": 0}}, {"09.05.2021": {"plan": 0, "fact": 0}}, {"10.05.2021": {"plan": 0, "fact": 0}}, {"11.05.2021": {"plan": 0, "fact": 0}}, {"12.05.2021": {"plan": 0, "fact": 0}}, {"13.05.2021": {"plan": 0, "fact": 0}}, {"14.05.2021": {"plan": 0, "fact": 0}}, {"15.05.2021": {"plan": 0, "fact": 0}}, {"16.05.2021": {"plan": 0, "fact": 0}}, {"17.05.2021": {"plan": 0, "fact": 0}}, {"18.05.2021": {"plan": 0, "fact": 0}}, {"19.05.2021": {"plan": 0, "fact": 0}}, {"20.05.2021": {"plan": 0, "fact": 0}}, {"21.05.2021": {"plan": 0, "fact": 0}}, {"22.05.2021": {"plan": 0, "fact": 0}}, {"23.05.2021": {"plan": 0, "fact": 0}}, {"24.05.2021": {"plan": 0, "fact": 0}}, {"25.05.2021": {"plan": 0, "fact": 0}}, {"26.05.2021": {"plan": 0, "fact": 0}}, {"27.05.2021": {"plan": 0, "fact": 0}}, {"28.05.2021": {"plan": 0, "fact": 0}}, {"29.05.2021": {"plan": 0, "fact": 0}}, {"30.05.2021": {"plan": 0, "fact": 0}}, {"31.05.2021": {"plan": 0, "fact": 0}}], "comments": null}, {"resource_id": null, "resource_name": "Покрасочный агрегат", "type": "equipment", "progress": [{"01.05.2021": {"plan": 0, "fact": 0}}, {"02.05.2021": {"plan": 0, "fact": 0}}, {"03.05.2021": {"plan": 0, "fact": 0}}, {"04.05.2021": {"plan": 0, "fact": 0}}, {"05.05.2021": {"plan": 0, "fact": 0}}, {"06.05.2021": {"plan": 0, "fact": 0}}, {"07.05.2021": {"plan": 0, "fact": 0}}, {"08.05.2021": {"plan": 0, "fact": 0}}, {"09.05.2021": {"plan": 0, "fact": 0}}, {"10.05.2021": {"plan": 0, "fact": 0}}, {"11.05.2021": {"plan": 0, "fact": 0}}, {"12.05.2021": {"plan": 0, "fact": 0}}, {"13.05.2021": {"plan": 0, "fact": 0}}, {"14.05.2021": {"plan": 0, "fact": 0}}, {"15.05.2021": {"plan": 0, "fact": 0}}, {"16.05.2021": {"plan": 0, "fact": 0}}, {"17.05.2021": {"plan": 0, "fact": 0}}, {"18.05.2021": {"plan": 0, "fact": 0}}, {"19.05.2021": {"plan": 0, "fact": 0}}, {"20.05.2021": {"plan": 0, "fact": 0}}, {"21.05.2021": {"plan": 0, "fact": 0}}, {"22.05.2021": {"plan": 0, "fact": 0}}, {"23.05.2021": {"plan": 0, "fact": 0}}, {"24.05.2021": {"plan": 0, "fact": 0}}, {"25.05.2021": {"plan": 0, "fact": 0}}, {"26.05.2021": {"plan": 0, "fact": 0}}, {"27.05.2021": {"plan": 0, "fact": 0}}, {"28.05.2021": {"plan": 0, "fact": 0}}, {"29.05.2021": {"plan": 0, "fact": 0}}, {"30.05.2021": {"plan": 0, "fact": 0}}, {"31.05.2021": {"plan": 0, "fact": 0}}], "comments": null}, {"resource_id": null, "resource_name": "ППУ (передвижная паровая установка)", "type": "equipment", "progress": [{"01.05.2021": {"plan": 0, "fact": 0}}, {"02.05.2021": {"plan": 0, "fact": 0}}, {"03.05.2021": {"plan": 0, "fact": 0}}, {"04.05.2021": {"plan": 0, "fact": 0}}, {"05.05.2021": {"plan": 0, "fact": 0}}, {"06.05.2021": {"plan": 0, "fact": 0}}, {"07.05.2021": {"plan": 0, "fact": 0}}, {"08.05.2021": {"plan": 0, "fact": 0}}, {"09.05.2021": {"plan": 0, "fact": 0}}, {"10.05.2021": {"plan": 0, "fact": 0}}, {"11.05.2021": {"plan": 0, "fact": 0}}, {"12.05.2021": {"plan": 0, "fact": 0}}, {"13.05.2021": {"plan": 0, "fact": 0}}, {"14.05.2021": {"plan": 0, "fact": 0}}, {"15.05.2021": {"plan": 0, "fact": 0}}, {"16.05.2021": {"plan": 0, "fact": 0}}, {"17.05.2021": {"plan": 0, "fact": 0}}, {"18.05.2021": {"plan": 0, "fact": 0}}, {"19.05.2021": {"plan": 0, "fact": 0}}, {"20.05.2021": {"plan": 0, "fact": 0}}, {"21.05.2021": {"plan": 0, "fact": 0}}, {"22.05.2021": {"plan": 0, "fact": 0}}, {"23.05.2021": {"plan": 0, "fact": 0}}, {"24.05.2021": {"plan": 0, "fact": 0}}, {"25.05.2021": {"plan": 0, "fact": 0}}, {"26.05.2021": {"plan": 0, "fact": 0}}, {"27.05.2021": {"plan": 0, "fact": 0}}, {"28.05.2021": {"plan": 0, "fact": 0}}, {"29.05.2021": {"plan": 0, "fact": 0}}, {"30.05.2021": {"plan": 0, "fact": 0}}, {"31.05.2021": {"plan": 0, "fact": 0}}], "comments": null}, {"resource_id": null, "resource_name": "ПСК (передвижной сварочный комплекс)", "type": "equipment", "progress": [{"01.05.2021": {"plan": 0, "fact": 0}}, {"02.05.2021": {"plan": 0, "fact": 0}}, {"03.05.2021": {"plan": 0, "fact": 0}}, {"04.05.2021": {"plan": 0, "fact": 0}}, {"05.05.2021": {"plan": 0, "fact": 0}}, {"06.05.2021": {"plan": 0, "fact": 0}}, {"07.05.2021": {"plan": 0, "fact": 0}}, {"08.05.2021": {"plan": 0, "fact": 0}}, {"09.05.2021": {"plan": 0, "fact": 0}}, {"10.05.2021": {"plan": 0, "fact": 0}}, {"11.05.2021": {"plan": 0, "fact": 0}}, {"12.05.2021": {"plan": 0, "fact": 0}}, {"13.05.2021": {"plan": 0, "fact": 0}}, {"14.05.2021": {"plan": 0, "fact": 0}}, {"15.05.2021": {"plan": 0, "fact": 0}}, {"16.05.2021": {"plan": 0, "fact": 0}}, {"17.05.2021": {"plan": 0, "fact": 0}}, {"18.05.2021": {"plan": 0, "fact": 0}}, {"19.05.2021": {"plan": 0, "fact": 0}}, {"20.05.2021": {"plan": 0, "fact": 0}}, {"21.05.2021": {"plan": 0, "fact": 0}}, {"22.05.2021": {"plan": 0, "fact": 0}}, {"23.05.2021": {"plan": 0, "fact": 0}}, {"24.05.2021": {"plan": 0, "fact": 0}}, {"25.05.2021": {"plan": 0, "fact": 0}}, {"26.05.2021": {"plan": 0, "fact": 0}}, {"27.05.2021": {"plan": 0, "fact": 0}}, {"28.05.2021": {"plan": 0, "fact": 0}}, {"29.05.2021": {"plan": 0, "fact": 0}}, {"30.05.2021": {"plan": 0, "fact": 0}}, {"31.05.2021": {"plan": 0, "fact": 0}}], "comments": null}, {"resource_id": null, "resource_name": "Самосвал", "type": "equipment", "progress": [{"01.05.2021": {"plan": 0, "fact": 0}}, {"02.05.2021": {"plan": 0, "fact": 0}}, {"03.05.2021": {"plan": 0, "fact": 0}}, {"04.05.2021": {"plan": 0, "fact": 0}}, {"05.05.2021": {"plan": 0, "fact": 0}}, {"06.05.2021": {"plan": 0, "fact": 0}}, {"07.05.2021": {"plan": 0, "fact": 0}}, {"08.05.2021": {"plan": 0, "fact": 0}}, {"09.05.2021": {"plan": 0, "fact": 0}}, {"10.05.2021": {"plan": 0, "fact": 0}}, {"11.05.2021": {"plan": 0, "fact": 0}}, {"12.05.2021": {"plan": 0, "fact": 0}}, {"13.05.2021": {"plan": 0, "fact": 0}}, {"14.05.2021": {"plan": 0, "fact": 0}}, {"15.05.2021": {"plan": 0, "fact": 0}}, {"16.05.2021": {"plan": 0, "fact": 0}}, {"17.05.2021": {"plan": 0, "fact": 0}}, {"18.05.2021": {"plan": 0, "fact": 0}}, {"19.05.2021": {"plan": 0, "fact": 0}}, {"20.05.2021": {"plan": 0, "fact": 0}}, {"21.05.2021": {"plan": 0, "fact": 0}}, {"22.05.2021": {"plan": 0, "fact": 0}}, {"23.05.2021": {"plan": 0, "fact": 0}}, {"24.05.2021": {"plan": 0, "fact": 0}}, {"25.05.2021": {"plan": 0, "fact": 0}}, {"26.05.2021": {"plan": 0, "fact": 0}}, {"27.05.2021": {"plan": 0, "fact": 0}}, {"28.05.2021": {"plan": 0, "fact": 0}}, {"29.05.2021": {"plan": 0, "fact": 0}}, {"30.05.2021": {"plan": 0, "fact": 0}}, {"31.05.2021": {"plan": 0, "fact": 0}}], "comments": null}, {"resource_id": null, "resource_name": "Сваебой", "type": "equipment", "progress": [{"01.05.2021": {"plan": 0, "fact": 0}}, {"02.05.2021": {"plan": 0, "fact": 0}}, {"03.05.2021": {"plan": 0, "fact": 0}}, {"04.05.2021": {"plan": 0, "fact": 0}}, {"05.05.2021": {"plan": 0, "fact": 0}}, {"06.05.2021": {"plan": 0, "fact": 0}}, {"07.05.2021": {"plan": 0, "fact": 0}}, {"08.05.2021": {"plan": 0, "fact": 0}}, {"09.05.2021": {"plan": 0, "fact": 0}}, {"10.05.2021": {"plan": 0, "fact": 0}}, {"11.05.2021": {"plan": 0, "fact": 0}}, {"12.05.2021": {"plan": 0, "fact": 0}}, {"13.05.2021": {"plan": 0, "fact": 0}}, {"14.05.2021": {"plan": 0, "fact": 0}}, {"15.05.2021": {"plan": 0, "fact": 0}}, {"16.05.2021": {"plan": 0, "fact": 0}}, {"17.05.2021": {"plan": 0, "fact": 0}}, {"18.05.2021": {"plan": 0, "fact": 0}}, {"19.05.2021": {"plan": 0, "fact": 0}}, {"20.05.2021": {"plan": 0, "fact": 0}}, {"21.05.2021": {"plan": 0, "fact": 0}}, {"22.05.2021": {"plan": 0, "fact": 0}}, {"23.05.2021": {"plan": 0, "fact": 0}}, {"24.05.2021": {"plan": 0, "fact": 0}}, {"25.05.2021": {"plan": 0, "fact": 0}}, {"26.05.2021": {"plan": 0, "fact": 0}}, {"27.05.2021": {"plan": 0, "fact": 0}}, {"28.05.2021": {"plan": 0, "fact": 0}}, {"29.05.2021": {"plan": 0, "fact": 0}}, {"30.05.2021": {"plan": 0, "fact": 0}}, {"31.05.2021": {"plan": 0, "fact": 0}}], "comments": null}, {"resource_id": null, "resource_name": "Сварочный комплекс", "type": "equipment", "progress": [{"01.05.2021": {"plan": 0, "fact": 0}}, {"02.05.2021": {"plan": 0, "fact": 0}}, {"03.05.2021": {"plan": 0, "fact": 0}}, {"04.05.2021": {"plan": 0, "fact": 0}}, {"05.05.2021": {"plan": 0, "fact": 0}}, {"06.05.2021": {"plan": 0, "fact": 0}}, {"07.05.2021": {"plan": 0, "fact": 0}}, {"08.05.2021": {"plan": 0, "fact": 0}}, {"09.05.2021": {"plan": 0, "fact": 0}}, {"10.05.2021": {"plan": 0, "fact": 0}}, {"11.05.2021": {"plan": 0, "fact": 0}}, {"12.05.2021": {"plan": 0, "fact": 0}}, {"13.05.2021": {"plan": 0, "fact": 0}}, {"14.05.2021": {"plan": 0, "fact": 0}}, {"15.05.2021": {"plan": 0, "fact": 0}}, {"16.05.2021": {"plan": 0, "fact": 0}}, {"17.05.2021": {"plan": 0, "fact": 0}}, {"18.05.2021": {"plan": 0, "fact": 0}}, {"19.05.2021": {"plan": 0, "fact": 0}}, {"20.05.2021": {"plan": 0, "fact": 0}}, {"21.05.2021": {"plan": 0, "fact": 0}}, {"22.05.2021": {"plan": 0, "fact": 0}}, {"23.05.2021": {"plan": 0, "fact": 0}}, {"24.05.2021": {"plan": 0, "fact": 0}}, {"25.05.2021": {"plan": 0, "fact": 0}}, {"26.05.2021": {"plan": 0, "fact": 0}}, {"27.05.2021": {"plan": 0, "fact": 0}}, {"28.05.2021": {"plan": 0, "fact": 0}}, {"29.05.2021": {"plan": 0, "fact": 0}}, {"30.05.2021": {"plan": 0, "fact": 0}}, {"31.05.2021": {"plan": 0, "fact": 0}}], "comments": null}, {"resource_id": null, "resource_name": "Трубоукладчик", "type": "equipment", "progress": [{"01.05.2021": {"plan": 0, "fact": 0}}, {"02.05.2021": {"plan": 0, "fact": 0}}, {"03.05.2021": {"plan": 0, "fact": 0}}, {"04.05.2021": {"plan": 0, "fact": 0}}, {"05.05.2021": {"plan": 0, "fact": 0}}, {"06.05.2021": {"plan": 0, "fact": 0}}, {"07.05.2021": {"plan": 0, "fact": 0}}, {"08.05.2021": {"plan": 0, "fact": 0}}, {"09.05.2021": {"plan": 0, "fact": 0}}, {"10.05.2021": {"plan": 0, "fact": 0}}, {"11.05.2021": {"plan": 0, "fact": 0}}, {"12.05.2021": {"plan": 0, "fact": 0}}, {"13.05.2021": {"plan": 0, "fact": 0}}, {"14.05.2021": {"plan": 0, "fact": 0}}, {"15.05.2021": {"plan": 0, "fact": 0}}, {"16.05.2021": {"plan": 0, "fact": 0}}, {"17.05.2021": {"plan": 0, "fact": 0}}, {"18.05.2021": {"plan": 0, "fact": 0}}, {"19.05.2021": {"plan": 0, "fact": 0}}, {"20.05.2021": {"plan": 0, "fact": 0}}, {"21.05.2021": {"plan": 0, "fact": 0}}, {"22.05.2021": {"plan": 0, "fact": 0}}, {"23.05.2021": {"plan": 0, "fact": 0}}, {"24.05.2021": {"plan": 0, "fact": 0}}, {"25.05.2021": {"plan": 0, "fact": 0}}, {"26.05.2021": {"plan": 0, "fact": 0}}, {"27.05.2021": {"plan": 0, "fact": 0}}, {"28.05.2021": {"plan": 0, "fact": 0}}, {"29.05.2021": {"plan": 0, "fact": 0}}, {"30.05.2021": {"plan": 0, "fact": 0}}, {"31.05.2021": {"plan": 0, "fact": 0}}], "comments": null}, {"resource_id": null, "resource_name": "Тягач, тягач седельный, трал", "type": "equipment", "progress": [{"01.05.2021": {"plan": 0, "fact": 0}}, {"02.05.2021": {"plan": 0, "fact": 0}}, {"03.05.2021": {"plan": 0, "fact": 0}}, {"04.05.2021": {"plan": 0, "fact": 0}}, {"05.05.2021": {"plan": 0, "fact": 0}}, {"06.05.2021": {"plan": 0, "fact": 0}}, {"07.05.2021": {"plan": 0, "fact": 0}}, {"08.05.2021": {"plan": 0, "fact": 0}}, {"09.05.2021": {"plan": 0, "fact": 0}}, {"10.05.2021": {"plan": 0, "fact": 0}}, {"11.05.2021": {"plan": 0, "fact": 0}}, {"12.05.2021": {"plan": 0, "fact": 0}}, {"13.05.2021": {"plan": 0, "fact": 0}}, {"14.05.2021": {"plan": 0, "fact": 0}}, {"15.05.2021": {"plan": 0, "fact": 0}}, {"16.05.2021": {"plan": 0, "fact": 0}}, {"17.05.2021": {"plan": 0, "fact": 0}}, {"18.05.2021": {"plan": 0, "fact": 0}}, {"19.05.2021": {"plan": 0, "fact": 0}}, {"20.05.2021": {"plan": 0, "fact": 0}}, {"21.05.2021": {"plan": 0, "fact": 0}}, {"22.05.2021": {"plan": 0, "fact": 0}}, {"23.05.2021": {"plan": 0, "fact": 0}}, {"24.05.2021": {"plan": 0, "fact": 0}}, {"25.05.2021": {"plan": 0, "fact": 0}}, {"26.05.2021": {"plan": 0, "fact": 0}}, {"27.05.2021": {"plan": 0, "fact": 0}}, {"28.05.2021": {"plan": 0, "fact": 0}}, {"29.05.2021": {"plan": 0, "fact": 0}}, {"30.05.2021": {"plan": 0, "fact": 0}}, {"31.05.2021": {"plan": 0, "fact": 0}}], "comments": null}, {"resource_id": null, "resource_name": "Прочая техника", "type": "equipment", "progress": [{"01.05.2021": {"plan": 0, "fact": 0}}, {"02.05.2021": {"plan": 0, "fact": 0}}, {"03.05.2021": {"plan": 0, "fact": 0}}, {"04.05.2021": {"plan": 0, "fact": 0}}, {"05.05.2021": {"plan": 0, "fact": 0}}, {"06.05.2021": {"plan": 0, "fact": 0}}, {"07.05.2021": {"plan": 0, "fact": 0}}, {"08.05.2021": {"plan": 0, "fact": 0}}, {"09.05.2021": {"plan": 0, "fact": 0}}, {"10.05.2021": {"plan": 0, "fact": 0}}, {"11.05.2021": {"plan": 0, "fact": 0}}, {"12.05.2021": {"plan": 0, "fact": 0}}, {"13.05.2021": {"plan": 0, "fact": 0}}, {"14.05.2021": {"plan": 0, "fact": 0}}, {"15.05.2021": {"plan": 0, "fact": 0}}, {"16.05.2021": {"plan": 0, "fact": 0}}, {"17.05.2021": {"plan": 0, "fact": 0}}, {"18.05.2021": {"plan": 0, "fact": 0}}, {"19.05.2021": {"plan": 0, "fact": 0}}, {"20.05.2021": {"plan": 0, "fact": 0}}, {"21.05.2021": {"plan": 0, "fact": 0}}, {"22.05.2021": {"plan": 0, "fact": 0}}, {"23.05.2021": {"plan": 0, "fact": 0}}, {"24.05.2021": {"plan": 0, "fact": 0}}, {"25.05.2021": {"plan": 0, "fact": 0}}, {"26.05.2021": {"plan": 0, "fact": 0}}, {"27.05.2021": {"plan": 0, "fact": 0}}, {"28.05.2021": {"plan": 0, "fact": 0}}, {"29.05.2021": {"plan": 0, "fact": 0}}, {"30.05.2021": {"plan": 0, "fact": 0}}, {"31.05.2021": {"plan": 0, "fact": 0}}], "comments": null}]}